Workbook

Sheet Resumen Comparativo
A1: CAMARONERA INDUSTRIAL — RESUMEN COMPARATIVO DE ESCENARIOS
A2: Fredy Valladares, Andrea Zambrano
A3: Comparación de métodos de amortización vs escenario sin financiamiento · Horizonte 10 años · Inversión Total: $5,400,000
A4: Método / Escenario | B4: Inversión Total ($) | C4: Financiamiento Bancario ($) | D4: WACC / Tasa de Corte | E4: VAN ($) | F4: TIR (%) | G4: PRI (años) | H4: PRID (años) | I4: ID (Índice Deseabilidad) | J4: Cuota Representativa ($)
A5: Sin Financiamiento | B5: ='Sin Financiamiento'!B77 -> 5400000 | C5: ='Sin Financiamiento'!B102 -> 0 | D5: ='Sin Financiamiento'!E150 -> 0.19 | E5: ='Sin Financiamiento'!B153 -> 3709755.7 | F5: ='Sin Financiamiento'!B154 -> 0.31148854 | G5: ='Sin Financiamiento'!B155 -> 4 | H5: ='Sin Financiamiento'!B156 -> 7 | I5: ='Sin Financiamiento'!B157 -> 1.6869918 | J5: "N/A"
A6: Método Francés (Annuity) | B6: =Francés!B77 -> 5400000 | C6: =Francés!B102 -> 2700000 | D6: =Francés!E150 -> 0.13 | E6: =Francés!B153 -> 7578967.3 | F6: =Francés!B154 -> 0.43681497 | G6: =Francés!B155 -> 4 | H6: =Francés!B156 -> 4 | I6: =Francés!B157 -> 3.8070249 | J6: =Francés!E109 -> 712253.2
A7: Método Americano (Bullet) | B7: =Americano!B77 -> 5400000 | C7: =Americano!B102 -> 2700000 | D7: =Americano!E150 -> 0.13 | E7: =Americano!B153 -> 7720019.7 | F7: =Americano!B154 -> 0.46244432 | G7: =Americano!B155 -> 3 | H7: =Americano!B156 -> 4 | I7: =Americano!B157 -> 3.8592666 | J7: =Americano!C109 -> 270000
A8: Método Italiano (Amort. Constante) | B8: =Italiano!B77 -> 5400000 | C8: =Italiano!B102 -> 2700000 | D8: =Italiano!E150 -> 0.13 | E8: =Italiano!B153 -> 7462388.8 | F8: =Italiano!B154 -> 0.40616532 | G8: =Italiano!B155 -> 4 | H8: =Italiano!B156 -> 5 | I8: =Italiano!B157 -> 3.7638477 | J8: =Italiano!C109 -> 655714.29
A9: Método Alemán (Gradiente) | B9: =Alemán!B77 -> 5400000 | C9: =Alemán!B102 -> 2700000 | D9: =Alemán!E150 -> 0.13 | E9: =Alemán!B153 -> 7412087.8 | F9: =Alemán!B154 -> 0.41162025 | G9: =Alemán!B155 -> 4 | H9: =Alemán!B156 -> 5 | I9: =Alemán!B157 -> 3.4956525 | J9: =Alemán!C109 -> 270000
A10: MEJOR VALOR POR INDICADOR | B10: =MIN(B5:B9) -> 5400000 | C10: =MAX(C5:C9) -> 2700000 | D10: =MIN(D5:D9) -> 0.13 | E10: =MAX(E5:E9) -> 7720019.7 | F10: =MAX(F5:F9) -> 0.46244432 | G10: =MIN(G5:G9) -> 3 | H10: =MIN(H5:H9) -> 4 | I10: =MAX(I5:I9) -> 3.8592666 | J10: =MIN(J5:J9) -> 270000

Sheet Sin Financiamiento
A1: Camaronera Industrial
A3: Variables
A4: Horizonte de evaluación (años) | B4: 10
A5: Devaluación | B5: 0.05
A6: Inflación | B6: 0.07
B7: Año 0 | C7: Año 1 | D7: Año 2 | E7: Año 3 | F7: Año 4 | G7: Año 5 | H7: Año 6 | I7: Año 7 | J7: Año 8 | K7: Año 9 | L7: Año 10
A8: Área en producción (Ha) | C8: 750 | D8: 900 | E8: 900 | F8: 900 | G8: 900 | H8: 900 | I8: 900 | J8: 900 | K8: 900 | L8: 900
A9: Producción neta (Lb/Ha/año) | C9: =1225 -> 1225 | D9: =1470 -> 1470 | E9: =1715 -> 1715 | F9: =1960 -> 1960 | G9: =2205 -> 2205 | H9: =2205 -> 2205 | I9: =2205 -> 2205 | J9: =2205 -> 2205 | K9: =2205 -> 2205 | L9: =2205 -> 2205
A10: Producción neta total (Lb/año) | C10: =C9*C8 -> 918750 | D10: =D9*D8 -> 1323000 | E10: =E9*E8 -> 1543500 | F10: =F9*F8 -> 1764000 | G10: =G9*G8 -> 1984500 | H10: =H9*H8 -> 1984500 | I10: =I9*I8 -> 1984500 | J10: =J9*J8 -> 1984500 | ... L10: =L9*L8 -> 1984500
A11: Tasa de cambio | C11: 1 | D11: =C11+(C11*$B$5) -> 1.05 | E11: =D11+(D11*$B$5) -> 1.1025 | F11: =E11+(E11*$B$5) -> 1.157625 | G11: =F11+(F11*$B$5) -> 1.2155063 | H11: =G11+(G11*$B$5) -> 1.2762816 | I11: =H11+(H11*$B$5) -> 1.3400956 | J11: =I11+(I11*$B$5) -> 1.4071004 | K11: =J11+(J11*$B$5) -> 1.4774554 | L11: =K11+(K11*$B$5) -> 1.5513282
A12: Precio de venta FOB ($/Lb) | C12: 3 | D12: =C12+(C12*$B$6) -> 3.21 | E12: =D12+(D12*$B$6) -> 3.4347 | F12: =E12+(E12*$B$6) -> 3.675129 | G12: =F12+(F12*$B$6) -> 3.932388 | H12: =G12+(G12*$B$6) -> 4.2076552 | I12: =H12+(H12*$B$6) -> 4.5021911 | J12: =I12+(I12*$B$6) -> 4.8173444 | K12: =J12+(J12*$B$6) -> 5.1545585 | L12: =K12+(K12*$B$6) -> 5.5153776
A13: Capital de trabajo | C13: 450000 | D13: 250000 | E13: 250000 | F13: 250000 | G13: 250000 | H13: 250000 | I13: 0 | J13: 0 | K13: 0 | L13: 0
A14: Costos variables ($1.45 x Lb) | C14: =1.45 -> 1.45 | D14: =C14+(C14*$B$6) -> 1.5515 | E14: =D14+(D14*$B$6) -> 1.660105 | F14: =E14+(E14*$B$6) -> 1.7763123 | G14: =F14+(F14*$B$6) -> 1.9006542 | H14: =G14+(G14*$B$6) -> 2.0337 | I14: =H14+(H14*$B$6) -> 2.176059 | J14: =I14+(I14*$B$6) -> 2.3283831 | K14: =J14+(J14*$B$6) -> 2.49137 | L14: =K14+(K14*$B$6) -> 2.6657659
A15: Costos variables anuales | C15: =C14*C10 -> 1332187.5 | D15: =D14*D10 -> 2052634.5 | E15: =E14*E10 -> 2562372.1 | F15: =F14*F10 -> 3133415 | G15: =G14*G10 -> 3771848.3 | H15: =H14*H10 -> 4035877.7 | I15: =I14*I10 -> 4318389.1 | J15: =J14*J10 -> 4620676.3 | ... L15: =L14*L10 -> 5290212.3
A16: Costos fijos de producción | C16: 50000 | D16: =C16+(C16*$B$6) -> 53500 | E16: =D16+(D16*$B$6) -> 57245 | F16: =E16+(E16*$B$6) -> 61252.15 | G16: =F16+(F16*$B$6) -> 65539.8 | H16: =G16+(G16*$B$6) -> 70127.587 | I16: =H16+(H16*$B$6) -> 75036.518 | J16: =I16+(I16*$B$6) -> 80289.074 | K16: =J16+(J16*$B$6) -> 85909.309 | L16: =K16+(K16*$B$6) -> 91922.961
A17: Gastos administrativos | C17: 200000 | D17: =C17+(C17*$B$6) -> 214000 | E17: =D17+(D17*$B$6) -> 228980 | F17: =E17+(E17*$B$6) -> 245008.6 | G17: =F17+(F17*$B$6) -> 262159.2 | H17: =G17+(G17*$B$6) -> 280510.35 | I17: =H17+(H17*$B$6) -> 300146.07 | J17: =I17+(I17*$B$6) -> 321156.3 | K17: =J17+(J17*$B$6) -> 343637.24 | L17: =K17+(K17*$B$6) -> 367691.84
A19: Valor residual del terreno | B19: 1250000
A20: Valor residual de estanques y canales | B20: 1000000
A21: Valor residual de edificios | B21: 50000
A22: Tasa de fiananciamiento bancario | B22: 0.1
A23: Plazo del financiamiento bancario (años) | B23: 7
A24: Plazo del financiamiento bancario (valor) | B24: =5400000*0.5 -> 2700000
A25: Tasa de corte | B25: 0.19
A26: Tasa de ISR | B26: 0.3
A28: 1. Ingresos del proyecto
A29: Calendario de ingresos (venta del producto)
A30: Concepto | B30: Año 0 | C30: Año 1 | D30: Año 2 | E30: Año 3 | F30: Año 4 | G30: Año 5 | H30: Año 6 | I30: Año 7 | J30: Año 8 | K30: Año 9 | L30: Año 10
A31: Cantidad de camarón (Lb) | C31: =C10 -> 918750 | D31: =D10 -> 1323000 | E31: =E10 -> 1543500 | F31: =F10 -> 1764000 | G31: =G10 -> 1984500 | H31: =H10 -> 1984500 | I31: =I10 -> 1984500 | J31: =J10 -> 1984500 | ... L31: =L10 -> 1984500
A32: Precio unitario de venta ($/Lb) | C32: =C12 -> 3 | D32: =D12 -> 3.21 | E32: =E12 -> 3.4347 | F32: =F12 -> 3.675129 | G32: =G12 -> 3.932388 | H32: =H12 -> 4.2076552 | I32: =I12 -> 4.5021911 | J32: =J12 -> 4.8173444 | ... L32: =L12 -> 5.5153776
A33: Ingresos | C33: =C32*C31 -> 2756250 | D33: =D32*D31 -> 4246830 | E33: =E32*E31 -> 5301459.5 | F33: =F32*F31 -> 6482927.6 | G33: =G32*G31 -> 7803824 | H33: =H32*H31 -> 8350091.7 | I33: =I32*I31 -> 8934598.1 | J33: =J32*J31 -> 9560020 | ... L33: =L32*L31 -> 10945267
A35: 2. Costos variables
A36: Calendario de costos variables
A37: Concepto | B37: Año 0 | C37: Año 1 | D37: Año 2 | E37: Año 3 | F37: Año 4 | G37: Año 5 | H37: Año 6 | I37: Año 7 | J37: Año 8 | K37: Año 9 | L37: Año 10
A38: Costos variables | C38: =C15 -> 1332187.5 | D38: =D15 -> 2052634.5 | E38: =E15 -> 2562372.1 | F38: =F15 -> 3133415 | G38: =G15 -> 3771848.3 | H38: =H15 -> 4035877.7 | I38: =I15 -> 4318389.1 | J38: =J15 -> 4620676.3 | ... L38: =L15 -> 5290212.3
A39: Total de costos variables | C39: =C38 -> 1332187.5 | D39: =D38 -> 2052634.5 | E39: =E38 -> 2562372.1 | F39: =F38 -> 3133415 | G39: =G38 -> 3771848.3 | H39: =H38 -> 4035877.7 | I39: =I38 -> 4318389.1 | J39: =J38 -> 4620676.3 | ... L39: =L38 -> 5290212.3
A41: 3. Costos fijos
A42: Calendario de los costos fijos
A43: Concepto | B43: Año 0 | C43: Año 1 | D43: Año 2 | E43: Año 3 | F43: Año 4 | G43: Año 5 | H43: Año 6 | I43: Año 7 | J43: Año 8 | K43: Año 9 | L43: Año 10
A44: Costos fijos de producción | C44: =C16 -> 50000 | D44: =D16 -> 53500 | E44: =E16 -> 57245 | F44: =F16 -> 61252.15 | G44: =G16 -> 65539.8 | H44: =H16 -> 70127.587 | I44: =I16 -> 75036.518 | J44: =J16 -> 80289.074 | ... L44: =L16 -> 91922.961
A45: Gastos administrativos | C45: =C17 -> 200000 | D45: =D17 -> 214000 | E45: =E17 -> 228980 | F45: =F17 -> 245008.6 | G45: =G17 -> 262159.2 | H45: =H17 -> 280510.35 | I45: =I17 -> 300146.07 | J45: =J17 -> 321156.3 | ... L45: =L17 -> 367691.84
A46: Total de costos fijos | C46: =SUM(C44:C45) -> 250000 | D46: =SUM(D44:D45) -> 267500 | E46: =SUM(E44:E45) -> 286225 | F46: =SUM(F44:F45) -> 306260.75 | G46: =SUM(G44:G45) -> 327699 | H46: =SUM(H44:H45) -> 350637.93 | I46: =SUM(I44:I45) -> 375182.59 | J46: =SUM(J44:J45) -> 401445.37 | ... L46: =SUM(L44:L45) -> 459614.8
A48: 4. Capital de trabajo
A49: Capital de trabajo
A50: Necesidad de Efectivo
A51: Concepto | B51: Año 0 | C51: Año 1 | D51: Año 2 | E51: Año 3 | F51: Año 4 | G51: Año 5 | H51: Año 6 | I51: Año 7 | J51: Año 8 | K51: Año 9 | L51: Año 10
A52: Capital de trabajo | C52: =C13+B52 -> 450000 | D52: =D13+C52 -> 700000 | E52: =E13+D52 -> 950000 | F52: =F13+E52 -> 1200000 | G52: =G13+F52 -> 1450000 | H52: =H13+G52 -> 1700000 | I52: =I13+H52 -> 1700000 | J52: =J13+I52 -> 1700000 | ... L52: =L13+K52 -> 1700000
A53: Efectivo requerido en caja | C53: =SUM(C52:C52) -> 450000 | D53: =SUM(D52:D52) -> 700000 | E53: =SUM(E52:E52) -> 950000 | F53: =SUM(F52:F52) -> 1200000 | G53: =SUM(G52:G52) -> 1450000 | H53: =SUM(H52:H52) -> 1700000 | I53: =SUM(I52:I52) -> 1700000 | J53: =SUM(J52:J52) -> 1700000 | ... L53: =SUM(L52:L52) -> 1700000
A55: Cálculo del Capital de Trabajo
A56: Concepto | B56: Cobertura | C56: Año 1 | D56: Año 2 | E56: Año 3 | F56: Año 4 | G56: Año 5 | H56: Año 6 | I56: Año 7 | J56: Año 8 | K56: Año 9 | L56: Año 10
A57: Activo circulante | C57: =C58 -> 450000 | D57: =D58 -> 700000 | E57: =E58 -> 950000 | F57: =F58 -> 1200000 | G57: =G58 -> 1450000 | H57: =H58 -> 1700000 | I57: =I58 -> 1700000 | J57: =J58 -> 1700000 | ... L57: =L58 -> 1700000
A58: Efectivo | C58: =C53 -> 450000 | D58: =D53 -> 700000 | E58: =E53 -> 950000 | F58: =F53 -> 1200000 | G58: =G53 -> 1450000 | H58: =H53 -> 1700000 | I58: =I53 -> 1700000 | J58: =J53 -> 1700000 | ... L58: =L53 -> 1700000
A59: Pasivo circulante | C59: =SUM(C60:C61) -> 0 | D59: =SUM(D60:D61) -> 0 | E59: =SUM(E60:E61) -> 0 | F59: =SUM(F60:F61) -> 0 | G59: =SUM(G60:G61) -> 0 | H59: =SUM(H60:H61) -> 0 | I59: =SUM(I60:I61) -> 0 | J59: =SUM(J60:J61) -> 0 | ... L59: =SUM(L60:L61) -> 0
A60: Cuentas por pagar | C60: 0 | D60: 0 | E60: 0 | F60: 0 | G60: 0 | H60: 0 | I60: 0 | J60: 0 | K60: 0 | L60: 0
A61: Proveedores | C61: 0 | D61: 0 | E61: 0 | F61: 0 | G61: 0 | H61: 0 | I61: 0 | J61: 0 | K61: 0 | L61: 0
A62: Capital de Trabajo (Ac - Pc) | C62: =C57-C59 -> 450000 | D62: =D57-D59 -> 700000 | E62: =E57-E59 -> 950000 | F62: =F57-F59 -> 1200000 | G62: =G57-G59 -> 1450000 | H62: =H57-H59 -> 1700000 | I62: =I57-I59 -> 1700000 | J62: =J57-J59 -> 1700000 | ... L62: =L57-L59 -> 1700000
A63: Incremento Capital Trabajo | B63: =C62-B62 -> 450000 | C63: =D62-C62 -> 250000 | D63: =E62-D62 -> 250000 | E63: =F62-E62 -> 250000 | F63: =G62-F62 -> 250000 | G63: =H62-G62 -> 250000 | H63: =I62-H62 -> 0 | I63: =J62-I62 -> 0 | ... L63: =M62-L62 -> -1700000
A65: 5. Inversiones
A66: Calendario de inversiones
A67: Concepto | B67: Año 0 | C67: Año 1 | D67: Año 2 | E67: Año 3 | F67: Año 4 | G67: Año 5 | H67: Año 6 | I67: Año 7 | J67: Año 8 | K67: Año 9 | L67: Año 10
A68: Activos Fijos
A69: Inversiones a 20 años | B69: 100000
A70: Inversiones a 10 años | B70: =3000000+200000+450000+50000 -> 3700000
A71: Inversiones a 5 años | B71: =300000+100000 -> 400000
A72: Inversion terrenos | B72: 750000
A73: Gastos Pre-operativos
A74: Gastos puesta en marcha | B74: 0
A75: Capital de trabajo
A76: Capital de trabajo | B76: =B63 -> 450000 | C76: =C63 -> 250000 | D76: =D63 -> 250000 | E76: =E63 -> 250000 | F76: =F63 -> 250000 | G76: =G63 -> 250000 | H76: =H63 -> 0 | I76: =I63 -> 0 | ... L76: =L63 -> -1700000
A77: Total Inversiones | B77: =SUM(B68:B76) -> 5400000 | C77: =SUM(C68:C76) -> 250000 | D77: =SUM(D68:D76) -> 250000 | E77: =SUM(E68:E76) -> 250000 | F77: =SUM(F68:F76) -> 250000 | G77: =SUM(G68:G76) -> 250000 | H77: =SUM(H68:H76) -> 0 | I77: =SUM(I68:I76) -> 0 | ... L77: =SUM(L68:L76) -> -1700000
A79: 6. Depreciaciones y Amortizaciones
A80: Calendario de Depreciaciones y Amortizaciones
A81: Concepto | B81: Año 0 | C81: Año 1 | D81: Año 2 | E81: Año 3 | F81: Año 4 | G81: Año 5 | H81: Año 6 | I81: Año 7 | J81: Año 8 | K81: Año 9 | L81: Año 10 | R81: Inversión | S81: Valor Activo | T81: Valor residual | U81: Vida útil | V81: Dep. Anual
A82: Inversiones a 20 años | C82: =$V$82 -> 2500 | D82: =$V$82 -> 2500 | E82: =$V$82 -> 2500 | F82: =$V$82 -> 2500 | G82: =$V$82 -> 2500 | H82: =$V$82 -> 2500 | I82: =$V$82 -> 2500 | J82: =$V$82 -> 2500 | ... L82: =$V$82 -> 2500 | R82: Edificio | S82: =B69 -> 100000 | T82: 50000 | U82: 20 | V82: =(S82-T82)/U82 -> 2500
A83: Inversiones a 10 años | C83: =$V$83+$V$84 -> 270000 | D83: =$V$83+$V$84 -> 270000 | E83: =$V$83+$V$84 -> 270000 | F83: =$V$83+$V$84 -> 270000 | G83: =$V$83+$V$84 -> 270000 | H83: =$V$83+$V$84 -> 270000 | I83: =$V$83+$V$84 -> 270000 | J83: =$V$83+$V$84 -> 270000 | ... L83: =$V$83+$V$84 -> 270000 | R83: Estanque y canales | S83: 3000000 | T83: 1000000 | U83: 10 | V83: =(S83-T83)/U83 -> 200000
A84: Inversiones a 5 años | C84: =$V$85 -> 80000 | D84: =$V$85 -> 80000 | E84: =$V$85 -> 80000 | F84: =$V$85 -> 80000 | G84: =$V$85 -> 80000 | H84: 0 | I84: 0 | J84: 0 | K84: 0 | L84: 0 | R84: Maq & Equipo | S84: =B70-S83 -> 700000 | T84: 0 | U84: 10 | V84: =(S84-T84)/U84 -> 70000
A85: Total Depreciación | C85: =SUM(C82:C84) -> 352500 | D85: =SUM(D82:D84) -> 352500 | E85: =SUM(E82:E84) -> 352500 | F85: =SUM(F82:F84) -> 352500 | G85: =SUM(G82:G84) -> 352500 | H85: =SUM(H82:H84) -> 272500 | I85: =SUM(I82:I84) -> 272500 | J85: =SUM(J82:J84) -> 272500 | ... L85: =SUM(L82:L84) -> 272500 | R85: Vehículos y embarcaciones | S85: =B71 -> 400000 | T85: 0 | U85: 5 | V85: =(S85-T85)/U85 -> 80000
S86: =SUM(S82:S85) -> 4200000
A87: Amortización pre-operativos | C87: =$B$74/10 -> 0 | D87: =$B$74/10 -> 0 | E87: =$B$74/10 -> 0 | F87: =$B$74/10 -> 0 | G87: =$B$74/10 -> 0 | H87: =$B$74/10 -> 0 | I87: =$B$74/10 -> 0 | J87: =$B$74/10 -> 0 | ... L87: =$B$74/10 -> 0
A88: Total Amortización | C88: =SUM(C87) -> 0 | D88: =SUM(D87) -> 0 | E88: =SUM(E87) -> 0 | F88: =SUM(F87) -> 0 | G88: =SUM(G87) -> 0 | H88: =SUM(H87) -> 0 | I88: =SUM(I87) -> 0 | J88: =SUM(J87) -> 0 | ... L88: =SUM(L87) -> 0
A90: 7. Valor de desecho del proyecto
A91: Clalculo del valor de desecho del proyecto (método contable)
A92: Concepto | B92: Valor del | C92: Depreciación por periodo | M92: Valor de
B93: Activo | C93: Año 1 | D93: Año 2 | E93: Año 3 | F93: Año 4 | G93: Año 5 | H93: Año 6 | I93: Año 7 | J93: Año 8 | K93: Año 9 | L93: Año 10 | M93: Desecho
A94: Inversiones a 20 años | B94: =B69 -> 100000 | C94: =C82 -> 2500 | D94: =D82 -> 2500 | E94: =E82 -> 2500 | F94: =F82 -> 2500 | G94: =G82 -> 2500 | H94: =H82 -> 2500 | I94: =I82 -> 2500 | J94: =J82 -> 2500 | ... L94: =L82 -> 2500 | M94: =B94-SUM(C94:L94) -> 75000
A95: Inversiones a 10 años | B95: =B70 -> 3700000 | C95: =C83 -> 270000 | D95: =D83 -> 270000 | E95: =E83 -> 270000 | F95: =F83 -> 270000 | G95: =G83 -> 270000 | H95: =H83 -> 270000 | I95: =I83 -> 270000 | J95: =J83 -> 270000 | ... L95: =L83 -> 270000 | M95: =B95-SUM(C95:L95) -> 1000000
A96: Inversiones a 5 años | B96: =B71 -> 400000 | C96: =C84 -> 80000 | D96: =D84 -> 80000 | E96: =E84 -> 80000 | F96: =F84 -> 80000 | G96: =G84 -> 80000 | H96: =H84 -> 0 | I96: =I84 -> 0 | J96: =J84 -> 0 | ... L96: =L84 -> 0 | M96: =B96-SUM(C96:L96) -> 0
A97: Amortización pre-operativos | B97: =B74 -> 0 | C97: =C87 -> 0 | D97: =D87 -> 0 | E97: =E87 -> 0 | F97: =F87 -> 0 | G97: =G87 -> 0 | H97: =H87 -> 0 | I97: =I87 -> 0 | J97: =J87 -> 0 | ... L97: =L87 -> 0 | M97: =B97-SUM(C97:L97) -> 0
A98: Valor de desecho total | M98: =SUM(M94:M97) -> 1075000
A100: 8. Financiamiento
A101: Cálculo del Financiamiento
A102: Financiamiento bancario (valor) | B102: =B77*E102 -> 0 | E102: 0
A103: Financiamiento bancario (tasa) | B103: =B22 -> 0.1
A104: Financiamiento bancario (periodos) | B104: 7 | C104: años
A105: Modalidad | B105: Pagos exactos
A107: Concepto | B107: Año 0 | C107: Año 1 | D107: Año 2 | E107: Año 3 | F107: Año 4 | G107: Año 5 | H107: Año 6 | I107: Año 7
A108: Saldo crédito | B108: =B102 -> 0 | C108: =B108-C111 -> 0 | D108: =C108-D111 -> 0 | E108: =D108-E111 -> 0 | F108: =E108-F111 -> 0 | G108: =F108-G111 -> 0 | H108: =G108-H111 -> 0 | I108: =H108-I111 -> 0
A109: Cuota mensual (anualidad) | C109: =C110 -> 0 | D109: =D110 -> 0 | E109: 0 | F109: 0 | G109: 0 | H109: 0 | I109: =(H108*B103)+H108 -> 0
A110: Intereses | C110: =B108*$B$103 -> 0 | D110: =C108*$B$103 -> 0 | E110: =D108*$B$103 -> 0 | F110: =E108*$B$103 -> 0 | G110: =F108*$B$103 -> 0 | H110: =G108*$B$103 -> 0 | I110: =H108*$B$103 -> 0
A111: Abono a capital (amortización) | C111: =C109-C110 -> 0 | D111: =D109-D110 -> 0 | E111: =E109-E110 -> 0 | F111: =F109-F110 -> 0 | G111: =G109-G110 -> 0 | H111: =H109-H110 -> 0 | I111: =I109-I110 -> 0
A113: 9.Flujo de caja del proyecto
...

Sheet PE$ sin Financiamiento
A1: Camaronera Industrial
A3: Variables
A4: Horizonte de evaluación (años) | B4: 10
A5: Devaluación | B5: 0.05
A6: Inflación | B6: 0.07
B7: Año 0 | C7: Año 1 | D7: Año 2 | E7: Año 3 | F7: Año 4 | G7: Año 5 | H7: Año 6 | I7: Año 7 | J7: Año 8 | K7: Año 9 | L7: Año 10
A8: Área en producción (Ha) | C8: 750 | D8: 900 | E8: 900 | F8: 900 | G8: 900 | H8: 900 | I8: 900 | J8: 900 | K8: 900 | L8: 900
A9: Producción neta (Lb/Ha/año) | C9: =1225 -> 1225 | D9: =1470 -> 1470 | E9: =1715 -> 1715 | F9: =1960 -> 1960 | G9: =2205 -> 2205 | H9: =2205 -> 2205 | I9: =2205 -> 2205 | J9: =2205 -> 2205 | K9: =2205 -> 2205 | L9: =2205 -> 2205
A10: Producción neta total (Lb/año) | C10: =C9*C8 -> 918750 | D10: =D9*D8 -> 1323000 | E10: =E9*E8 -> 1543500 | F10: =F9*F8 -> 1764000 | G10: =G9*G8 -> 1984500 | H10: =H9*H8 -> 1984500 | I10: =I9*I8 -> 1984500 | J10: =J9*J8 -> 1984500 | ... L10: =L9*L8 -> 1984500
A11: Tasa de cambio | C11: 1 | D11: =C11+(C11*$B$5) -> 1.05 | E11: =D11+(D11*$B$5) -> 1.1025 | F11: =E11+(E11*$B$5) -> 1.157625 | G11: =F11+(F11*$B$5) -> 1.2155063 | H11: =G11+(G11*$B$5) -> 1.2762816 | I11: =H11+(H11*$B$5) -> 1.3400956 | J11: =I11+(I11*$B$5) -> 1.4071004 | K11: =J11+(J11*$B$5) -> 1.4774554 | L11: =K11+(K11*$B$5) -> 1.5513282
A12: Precio de venta FOB ($/Lb) | C12: 2.4108299 | D12: =C12+(C12*$B$6) -> 2.579588 | E12: =D12+(D12*$B$6) -> 2.7601592 | F12: =E12+(E12*$B$6) -> 2.9533703 | G12: =F12+(F12*$B$6) -> 3.1601062 | H12: =G12+(G12*$B$6) -> 3.3813137 | I12: =H12+(H12*$B$6) -> 3.6180056 | J12: =I12+(I12*$B$6) -> 3.871266 | K12: =J12+(J12*$B$6) -> 4.1422546 | L12: =K12+(K12*$B$6) -> 4.4322124
A13: Capital de trabajo | C13: 450000 | D13: 250000 | E13: 250000 | F13: 250000 | G13: 250000 | H13: 250000 | I13: 0 | J13: 0 | K13: 0 | L13: 0
A14: Costos variables ($1.45 x Lb) | C14: =1.45 -> 1.45 | D14: =C14+(C14*$B$6) -> 1.5515 | E14: =D14+(D14*$B$6) -> 1.660105 | F14: =E14+(E14*$B$6) -> 1.7763123 | G14: =F14+(F14*$B$6) -> 1.9006542 | H14: =G14+(G14*$B$6) -> 2.0337 | I14: =H14+(H14*$B$6) -> 2.176059 | J14: =I14+(I14*$B$6) -> 2.3283831 | K14: =J14+(J14*$B$6) -> 2.49137 | L14: =K14+(K14*$B$6) -> 2.6657659
A15: Costos variables anuales | C15: =C14*C10 -> 1332187.5 | D15: =D14*D10 -> 2052634.5 | E15: =E14*E10 -> 2562372.1 | F15: =F14*F10 -> 3133415 | G15: =G14*G10 -> 3771848.3 | H15: =H14*H10 -> 4035877.7 | I15: =I14*I10 -> 4318389.1 | J15: =J14*J10 -> 4620676.3 | ... L15: =L14*L10 -> 5290212.3
A16: Costos fijos de producción | C16: 50000 | D16: =C16+(C16*$B$6) -> 53500 | E16: =D16+(D16*$B$6) -> 57245 | F16: =E16+(E16*$B$6) -> 61252.15 | G16: =F16+(F16*$B$6) -> 65539.8 | H16: =G16+(G16*$B$6) -> 70127.587 | I16: =H16+(H16*$B$6) -> 75036.518 | J16: =I16+(I16*$B$6) -> 80289.074 | K16: =J16+(J16*$B$6) -> 85909.309 | L16: =K16+(K16*$B$6) -> 91922.961
A17: Gastos administrativos | C17: 200000 | D17: =C17+(C17*$B$6) -> 214000 | E17: =D17+(D17*$B$6) -> 228980 | F17: =E17+(E17*$B$6) -> 245008.6 | G17: =F17+(F17*$B$6) -> 262159.2 | H17: =G17+(G17*$B$6) -> 280510.35 | I17: =H17+(H17*$B$6) -> 300146.07 | J17: =I17+(I17*$B$6) -> 321156.3 | K17: =J17+(J17*$B$6) -> 343637.24 | L17: =K17+(K17*$B$6) -> 367691.84
A19: Valor residual del terreno | B19: 1250000
A20: Valor residual de estanques y canales | B20: 1000000
A21: Valor residual de edificios | B21: 50000
A22: Tasa de fiananciamiento bancario | B22: 0.1
A23: Plazo del financiamiento bancario (años) | B23: 7
A24: Plazo del financiamiento bancario (valor) | B24: =5400000*0.5 -> 2700000
A25: Tasa de corte | B25: 0.19
A26: Tasa de ISR | B26: 0.3
A28: 1. Ingresos del proyecto
A29: Calendario de ingresos (venta del producto)
A30: Concepto | B30: Año 0 | C30: Año 1 | D30: Año 2 | E30: Año 3 | F30: Año 4 | G30: Año 5 | H30: Año 6 | I30: Año 7 | J30: Año 8 | K30: Año 9 | L30: Año 10
A31: Cantidad de camarón (Lb) | C31: =C10 -> 918750 | D31: =D10 -> 1323000 | E31: =E10 -> 1543500 | F31: =F10 -> 1764000 | G31: =G10 -> 1984500 | H31: =H10 -> 1984500 | I31: =I10 -> 1984500 | J31: =J10 -> 1984500 | ... L31: =L10 -> 1984500
A32: Precio unitario de venta ($/Lb) | C32: =C12 -> 2.4108299 | D32: =D12 -> 2.579588 | E32: =E12 -> 2.7601592 | F32: =F12 -> 2.9533703 | G32: =G12 -> 3.1601062 | H32: =H12 -> 3.3813137 | I32: =I12 -> 3.6180056 | J32: =J12 -> 3.871266 | ... L32: =L12 -> 4.4322124
A33: Ingresos | C33: =C32*C31 -> 2214950 | D33: =D32*D31 -> 3412794.9 | E33: =E32*E31 -> 4260305.7 | F33: =F32*F31 -> 5209745.2 | G33: =G32*G31 -> 6271230.8 | H33: =H32*H31 -> 6710216.9 | I33: =I32*I31 -> 7179932.1 | J33: =J32*J31 -> 7682527.4 | ... L33: =L32*L31 -> 8795725.6
A35: 2. Costos variables
A36: Calendario de costos variables
A37: Concepto | B37: Año 0 | C37: Año 1 | D37: Año 2 | E37: Año 3 | F37: Año 4 | G37: Año 5 | H37: Año 6 | I37: Año 7 | J37: Año 8 | K37: Año 9 | L37: Año 10
A38: Costos variables | C38: =C15 -> 1332187.5 | D38: =D15 -> 2052634.5 | E38: =E15 -> 2562372.1 | F38: =F15 -> 3133415 | G38: =G15 -> 3771848.3 | H38: =H15 -> 4035877.7 | I38: =I15 -> 4318389.1 | J38: =J15 -> 4620676.3 | ... L38: =L15 -> 5290212.3
A39: Total de costos variables | C39: =C38 -> 1332187.5 | D39: =D38 -> 2052634.5 | E39: =E38 -> 2562372.1 | F39: =F38 -> 3133415 | G39: =G38 -> 3771848.3 | H39: =H38 -> 4035877.7 | I39: =I38 -> 4318389.1 | J39: =J38 -> 4620676.3 | ... L39: =L38 -> 5290212.3
A41: 3. Costos fijos
A42: Calendario de los costos fijos
A43: Concepto | B43: Año 0 | C43: Año 1 | D43: Año 2 | E43: Año 3 | F43: Año 4 | G43: Año 5 | H43: Año 6 | I43: Año 7 | J43: Año 8 | K43: Año 9 | L43: Año 10
A44: Costos fijos de producción | C44: =C16 -> 50000 | D44: =D16 -> 53500 | E44: =E16 -> 57245 | F44: =F16 -> 61252.15 | G44: =G16 -> 65539.8 | H44: =H16 -> 70127.587 | I44: =I16 -> 75036.518 | J44: =J16 -> 80289.074 | ... L44: =L16 -> 91922.961
A45: Gastos administrativos | C45: =C17 -> 200000 | D45: =D17 -> 214000 | E45: =E17 -> 228980 | F45: =F17 -> 245008.6 | G45: =G17 -> 262159.2 | H45: =H17 -> 280510.35 | I45: =I17 -> 300146.07 | J45: =J17 -> 321156.3 | ... L45: =L17 -> 367691.84
A46: Total de costos fijos | C46: =SUM(C44:C45) -> 250000 | D46: =SUM(D44:D45) -> 267500 | E46: =SUM(E44:E45) -> 286225 | F46: =SUM(F44:F45) -> 306260.75 | G46: =SUM(G44:G45) -> 327699 | H46: =SUM(H44:H45) -> 350637.93 | I46: =SUM(I44:I45) -> 375182.59 | J46: =SUM(J44:J45) -> 401445.37 | ... L46: =SUM(L44:L45) -> 459614.8
A48: 4. Capital de trabajo
A49: Capital de trabajo
A50: Necesidad de Efectivo
A51: Concepto | B51: Año 0 | C51: Año 1 | D51: Año 2 | E51: Año 3 | F51: Año 4 | G51: Año 5 | H51: Año 6 | I51: Año 7 | J51: Año 8 | K51: Año 9 | L51: Año 10
A52: Capital de trabajo | C52: =C13+B52 -> 450000 | D52: =D13+C52 -> 700000 | E52: =E13+D52 -> 950000 | F52: =F13+E52 -> 1200000 | G52: =G13+F52 -> 1450000 | H52: =H13+G52 -> 1700000 | I52: =I13+H52 -> 1700000 | J52: =J13+I52 -> 1700000 | ... L52: =L13+K52 -> 1700000
A53: Efectivo requerido en caja | C53: =SUM(C52:C52) -> 450000 | D53: =SUM(D52:D52) -> 700000 | E53: =SUM(E52:E52) -> 950000 | F53: =SUM(F52:F52) -> 1200000 | G53: =SUM(G52:G52) -> 1450000 | H53: =SUM(H52:H52) -> 1700000 | I53: =SUM(I52:I52) -> 1700000 | J53: =SUM(J52:J52) -> 1700000 | ... L53: =SUM(L52:L52) -> 1700000
A55: Cálculo del Capital de Trabajo
A56: Concepto | B56: Cobertura | C56: Año 1 | D56: Año 2 | E56: Año 3 | F56: Año 4 | G56: Año 5 | H56: Año 6 | I56: Año 7 | J56: Año 8 | K56: Año 9 | L56: Año 10
A57: Activo circulante | C57: =C58 -> 450000 | D57: =D58 -> 700000 | E57: =E58 -> 950000 | F57: =F58 -> 1200000 | G57: =G58 -> 1450000 | H57: =H58 -> 1700000 | I57: =I58 -> 1700000 | J57: =J58 -> 1700000 | ... L57: =L58 -> 1700000
A58: Efectivo | C58: =C53 -> 450000 | D58: =D53 -> 700000 | E58: =E53 -> 950000 | F58: =F53 -> 1200000 | G58: =G53 -> 1450000 | H58: =H53 -> 1700000 | I58: =I53 -> 1700000 | J58: =J53 -> 1700000 | ... L58: =L53 -> 1700000
A59: Pasivo circulante | C59: =SUM(C60:C61) -> 0 | D59: =SUM(D60:D61) -> 0 | E59: =SUM(E60:E61) -> 0 | F59: =SUM(F60:F61) -> 0 | G59: =SUM(G60:G61) -> 0 | H59: =SUM(H60:H61) -> 0 | I59: =SUM(I60:I61) -> 0 | J59: =SUM(J60:J61) -> 0 | ... L59: =SUM(L60:L61) -> 0
A60: Cuentas por pagar | C60: 0 | D60: 0 | E60: 0 | F60: 0 | G60: 0 | H60: 0 | I60: 0 | J60: 0 | K60: 0 | L60: 0
A61: Proveedores | C61: 0 | D61: 0 | E61: 0 | F61: 0 | G61: 0 | H61: 0 | I61: 0 | J61: 0 | K61: 0 | L61: 0
A62: Capital de Trabajo (Ac - Pc) | C62: =C57-C59 -> 450000 | D62: =D57-D59 -> 700000 | E62: =E57-E59 -> 950000 | F62: =F57-F59 -> 1200000 | G62: =G57-G59 -> 1450000 | H62: =H57-H59 -> 1700000 | I62: =I57-I59 -> 1700000 | J62: =J57-J59 -> 1700000 | ... L62: =L57-L59 -> 1700000
A63: Incremento Capital Trabajo | B63: =C62-B62 -> 450000 | C63: =D62-C62 -> 250000 | D63: =E62-D62 -> 250000 | E63: =F62-E62 -> 250000 | F63: =G62-F62 -> 250000 | G63: =H62-G62 -> 250000 | H63: =I62-H62 -> 0 | I63: =J62-I62 -> 0 | ... L63: =M62-L62 -> -1700000
A65: 5. Inversiones
A66: Calendario de inversiones
A67: Concepto | B67: Año 0 | C67: Año 1 | D67: Año 2 | E67: Año 3 | F67: Año 4 | G67: Año 5 | H67: Año 6 | I67: Año 7 | J67: Año 8 | K67: Año 9 | L67: Año 10
A68: Activos Fijos
A69: Inversiones a 20 años | B69: 100000
A70: Inversiones a 10 años | B70: =3000000+200000+450000+50000 -> 3700000
A71: Inversiones a 5 años | B71: =300000+100000 -> 400000
A72: Inversion terrenos | B72: 750000
A73: Gastos Pre-operativos
A74: Gastos puesta en marcha | B74: 0
A75: Capital de trabajo
A76: Capital de trabajo | B76: =B63 -> 450000 | C76: =C63 -> 250000 | D76: =D63 -> 250000 | E76: =E63 -> 250000 | F76: =F63 -> 250000 | G76: =G63 -> 250000 | H76: =H63 -> 0 | I76: =I63 -> 0 | ... L76: =L63 -> -1700000
A77: Total Inversiones | B77: =SUM(B68:B76) -> 5400000 | C77: =SUM(C68:C76) -> 250000 | D77: =SUM(D68:D76) -> 250000 | E77: =SUM(E68:E76) -> 250000 | F77: =SUM(F68:F76) -> 250000 | G77: =SUM(G68:G76) -> 250000 | H77: =SUM(H68:H76) -> 0 | I77: =SUM(I68:I76) -> 0 | ... L77: =SUM(L68:L76) -> -1700000
A79: 6. Depreciaciones y Amortizaciones
A80: Calendario de Depreciaciones y Amortizaciones
A81: Concepto | B81: Año 0 | C81: Año 1 | D81: Año 2 | E81: Año 3 | F81: Año 4 | G81: Año 5 | H81: Año 6 | I81: Año 7 | J81: Año 8 | K81: Año 9 | L81: Año 10 | R81: Inversión | S81: Valor Activo | T81: Valor residual | U81: Vida útil | V81: Dep. Anual
A82: Inversiones a 20 años | C82: =$V$82 -> 2500 | D82: =$V$82 -> 2500 | E82: =$V$82 -> 2500 | F82: =$V$82 -> 2500 | G82: =$V$82 -> 2500 | H82: =$V$82 -> 2500 | I82: =$V$82 -> 2500 | J82: =$V$82 -> 2500 | ... L82: =$V$82 -> 2500 | R82: Edificio | S82: =B69 -> 100000 | T82: 50000 | U82: 20 | V82: =(S82-T82)/U82 -> 2500
A83: Inversiones a 10 años | C83: =$V$83+$V$84 -> 270000 | D83: =$V$83+$V$84 -> 270000 | E83: =$V$83+$V$84 -> 270000 | F83: =$V$83+$V$84 -> 270000 | G83: =$V$83+$V$84 -> 270000 | H83: =$V$83+$V$84 -> 270000 | I83: =$V$83+$V$84 -> 270000 | J83: =$V$83+$V$84 -> 270000 | ... L83: =$V$83+$V$84 -> 270000 | R83: Estanque y canales | S83: 3000000 | T83: 1000000 | U83: 10 | V83: =(S83-T83)/U83 -> 200000
A84: Inversiones a 5 años | C84: =$V$85 -> 80000 | D84: =$V$85 -> 80000 | E84: =$V$85 -> 80000 | F84: =$V$85 -> 80000 | G84: =$V$85 -> 80000 | H84: 0 | I84: 0 | J84: 0 | K84: 0 | L84: 0 | R84: Maq & Equipo | S84: =B70-S83 -> 700000 | T84: 0 | U84: 10 | V84: =(S84-T84)/U84 -> 70000
A85: Total Depreciación | C85: =SUM(C82:C84) -> 352500 | D85: =SUM(D82:D84) -> 352500 | E85: =SUM(E82:E84) -> 352500 | F85: =SUM(F82:F84) -> 352500 | G85: =SUM(G82:G84) -> 352500 | H85: =SUM(H82:H84) -> 272500 | I85: =SUM(I82:I84) -> 272500 | J85: =SUM(J82:J84) -> 272500 | ... L85: =SUM(L82:L84) -> 272500 | R85: Vehículos y embarcaciones | S85: =B71 -> 400000 | T85: 0 | U85: 5 | V85: =(S85-T85)/U85 -> 80000
S86: =SUM(S82:S85) -> 4200000
A87: Amortización pre-operativos | C87: =$B$74/10 -> 0 | D87: =$B$74/10 -> 0 | E87: =$B$74/10 -> 0 | F87: =$B$74/10 -> 0 | G87: =$B$74/10 -> 0 | H87: =$B$74/10 -> 0 | I87: =$B$74/10 -> 0 | J87: =$B$74/10 -> 0 | ... L87: =$B$74/10 -> 0
A88: Total Amortización | C88: =SUM(C87) -> 0 | D88: =SUM(D87) -> 0 | E88: =SUM(E87) -> 0 | F88: =SUM(F87) -> 0 | G88: =SUM(G87) -> 0 | H88: =SUM(H87) -> 0 | I88: =SUM(I87) -> 0 | J88: =SUM(J87) -> 0 | ... L88: =SUM(L87) -> 0
A90: 7. Valor de desecho del proyecto
A91: Clalculo del valor de desecho del proyecto (método contable)
A92: Concepto | B92: Valor del | C92: Depreciación por periodo | M92: Valor de
B93: Activo | C93: Año 1 | D93: Año 2 | E93: Año 3 | F93: Año 4 | G93: Año 5 | H93: Año 6 | I93: Año 7 | J93: Año 8 | K93: Año 9 | L93: Año 10 | M93: Desecho
A94: Inversiones a 20 años | B94: =B69 -> 100000 | C94: =C82 -> 2500 | D94: =D82 -> 2500 | E94: =E82 -> 2500 | F94: =F82 -> 2500 | G94: =G82 -> 2500 | H94: =H82 -> 2500 | I94: =I82 -> 2500 | J94: =J82 -> 2500 | ... L94: =L82 -> 2500 | M94: =B94-SUM(C94:L94) -> 75000
A95: Inversiones a 10 años | B95: =B70 -> 3700000 | C95: =C83 -> 270000 | D95: =D83 -> 270000 | E95: =E83 -> 270000 | F95: =F83 -> 270000 | G95: =G83 -> 270000 | H95: =H83 -> 270000 | I95: =I83 -> 270000 | J95: =J83 -> 270000 | ... L95: =L83 -> 270000 | M95: =B95-SUM(C95:L95) -> 1000000
A96: Inversiones a 5 años | B96: =B71 -> 400000 | C96: =C84 -> 80000 | D96: =D84 -> 80000 | E96: =E84 -> 80000 | F96: =F84 -> 80000 | G96: =G84 -> 80000 | H96: =H84 -> 0 | I96: =I84 -> 0 | J96: =J84 -> 0 | ... L96: =L84 -> 0 | M96: =B96-SUM(C96:L96) -> 0
A97: Amortización pre-operativos | B97: =B74 -> 0 | C97: =C87 -> 0 | D97: =D87 -> 0 | E97: =E87 -> 0 | F97: =F87 -> 0 | G97: =G87 -> 0 | H97: =H87 -> 0 | I97: =I87 -> 0 | J97: =J87 -> 0 | ... L97: =L87 -> 0 | M97: =B97-SUM(C97:L97) -> 0
A98: Valor de desecho total | M98: =SUM(M94:M97) -> 1075000
A100: 8. Financiamiento
A101: Cálculo del Financiamiento
A102: Financiamiento bancario (valor) | B102: =B77*E102 -> 0 | E102: 0
A103: Financiamiento bancario (tasa) | B103: =B22 -> 0.1
A104: Financiamiento bancario (periodos) | B104: 7 | C104: años
A105: Modalidad | B105: Pagos exactos
A107: Concepto | B107: Año 0 | C107: Año 1 | D107: Año 2 | E107: Año 3 | F107: Año 4 | G107: Año 5 | H107: Año 6 | I107: Año 7
A108: Saldo crédito | B108: =B102 -> 0 | C108: =B108-C111 -> 0 | D108: =C108-D111 -> 0 | E108: =D108-E111 -> 0 | F108: =E108-F111 -> 0 | G108: =F108-G111 -> 0 | H108: =G108-H111 -> 0 | I108: =H108-I111 -> 0
A109: Cuota mensual (anualidad) | C109: =C110 -> 0 | D109: =D110 -> 0 | E109: 0 | F109: 0 | G109: 0 | H109: 0 | I109: =(H108*B103)+H108 -> 0
A110: Intereses | C110: =B108*$B$103 -> 0 | D110: =C108*$B$103 -> 0 | E110: =D108*$B$103 -> 0 | F110: =E108*$B$103 -> 0 | G110: =F108*$B$103 -> 0 | H110: =G108*$B$103 -> 0 | I110: =H108*$B$103 -> 0
A111: Abono a capital (amortización) | C111: =C109-C110 -> 0 | D111: =D109-D110 -> 0 | E111: =E109-E110 -> 0 | F111: =F109-F110 -> 0 | G111: =G109-G110 -> 0 | H111: =H109-H110 -> 0 | I111: =I109-I110 -> 0
A113: 9.Flujo de caja del proyecto
...

Sheet PEx sin Financiamiento
A1: Camaronera Industrial
A3: Variables
A4: Horizonte de evaluación (años) | B4: 10
A5: Devaluación | B5: 0.05
A6: Inflación | B6: 0.07
B7: Año 0 | C7: Año 1 | D7: Año 2 | E7: Año 3 | F7: Año 4 | G7: Año 5 | H7: Año 6 | I7: Año 7 | J7: Año 8 | K7: Año 9 | L7: Año 10
A8: Área en producción (Ha) | C8: 750 | D8: 900 | E8: 900 | F8: 900 | G8: 900 | H8: 900 | I8: 900 | J8: 900 | K8: 900 | L8: 900
A9: Producción neta (Lb/Ha/año) | C9: =1225 -> 1225 | D9: =1470 -> 1470 | E9: =1715 -> 1715 | F9: =1960 -> 1960 | G9: =2205 -> 2205 | H9: =2205 -> 2205 | I9: =2205 -> 2205 | J9: =2205 -> 2205 | K9: =2205 -> 2205 | L9: =2205 -> 2205
A10: Producción neta total (Lb/año) | C10: =C9*C8 -> 918750 | D10: =D9*D8 -> 1323000 | E10: =E9*E8 -> 1543500 | F10: =F9*F8 -> 1764000 | G10: =G9*G8 -> 1984500 | H10: =H9*H8 -> 1984500 | I10: =I9*I8 -> 1984500 | J10: =J9*J8 -> 1984500 | ... L10: =L9*L8 -> 1984500
A11: Tasa de cambio | C11: 1 | D11: =C11+(C11*$B$5) -> 1.05 | E11: =D11+(D11*$B$5) -> 1.1025 | F11: =E11+(E11*$B$5) -> 1.157625 | G11: =F11+(F11*$B$5) -> 1.2155063 | H11: =G11+(G11*$B$5) -> 1.2762816 | I11: =H11+(H11*$B$5) -> 1.3400956 | J11: =I11+(I11*$B$5) -> 1.4071004 | K11: =J11+(J11*$B$5) -> 1.4774554 | L11: =K11+(K11*$B$5) -> 1.5513282
A12: Precio de venta FOB ($/Lb) | C12: 3 | D12: =C12+(C12*$B$6) -> 3.21 | E12: =D12+(D12*$B$6) -> 3.4347 | F12: =E12+(E12*$B$6) -> 3.675129 | G12: =F12+(F12*$B$6) -> 3.932388 | H12: =G12+(G12*$B$6) -> 4.2076552 | I12: =H12+(H12*$B$6) -> 4.5021911 | J12: =I12+(I12*$B$6) -> 4.8173444 | K12: =J12+(J12*$B$6) -> 5.1545585 | L12: =K12+(K12*$B$6) -> 5.5153776
A13: Capital de trabajo | C13: 450000 | D13: 250000 | E13: 250000 | F13: 250000 | G13: 250000 | H13: 250000 | I13: 0 | J13: 0 | K13: 0 | L13: 0
A14: Costos variables ($1.45 x Lb) | C14: =1.45 -> 1.45 | D14: =C14+(C14*$B$6) -> 1.5515 | E14: =D14+(D14*$B$6) -> 1.660105 | F14: =E14+(E14*$B$6) -> 1.7763123 | G14: =F14+(F14*$B$6) -> 1.9006542 | H14: =G14+(G14*$B$6) -> 2.0337 | I14: =H14+(H14*$B$6) -> 2.176059 | J14: =I14+(I14*$B$6) -> 2.3283831 | K14: =J14+(J14*$B$6) -> 2.49137 | L14: =K14+(K14*$B$6) -> 2.6657659
A15: Costos variables anuales | C15: =C14*C10 -> 1332187.5 | D15: =D14*D10 -> 2052634.5 | E15: =E14*E10 -> 2562372.1 | F15: =F14*F10 -> 3133415 | G15: =G14*G10 -> 3771848.3 | H15: =H14*H10 -> 4035877.7 | I15: =I14*I10 -> 4318389.1 | J15: =J14*J10 -> 4620676.3 | ... L15: =L14*L10 -> 5290212.3
A16: Costos fijos de producción | C16: 50000 | D16: =C16+(C16*$B$6) -> 53500 | E16: =D16+(D16*$B$6) -> 57245 | F16: =E16+(E16*$B$6) -> 61252.15 | G16: =F16+(F16*$B$6) -> 65539.8 | H16: =G16+(G16*$B$6) -> 70127.587 | I16: =H16+(H16*$B$6) -> 75036.518 | J16: =I16+(I16*$B$6) -> 80289.074 | K16: =J16+(J16*$B$6) -> 85909.309 | L16: =K16+(K16*$B$6) -> 91922.961
A17: Gastos administrativos | C17: 200000 | D17: =C17+(C17*$B$6) -> 214000 | E17: =D17+(D17*$B$6) -> 228980 | F17: =E17+(E17*$B$6) -> 245008.6 | G17: =F17+(F17*$B$6) -> 262159.2 | H17: =G17+(G17*$B$6) -> 280510.35 | I17: =H17+(H17*$B$6) -> 300146.07 | J17: =I17+(I17*$B$6) -> 321156.3 | K17: =J17+(J17*$B$6) -> 343637.24 | L17: =K17+(K17*$B$6) -> 367691.84
A19: Valor residual del terreno | B19: 1250000
A20: Valor residual de estanques y canales | B20: 1000000
A21: Valor residual de edificios | B21: 50000
A22: Tasa de fiananciamiento bancario | B22: 0.1
A23: Plazo del financiamiento bancario (años) | B23: 7
A24: Plazo del financiamiento bancario (valor) | B24: =5400000*0.5 -> 2700000
A25: Tasa de corte | B25: 0.19
A26: Tasa de ISR | B26: 0.3
D27: 0.44 | E27: 0.16666667 | F27: 0.14285714 | G27: 0.125 | H27: 0 | I27: 0 | J27: 0 | K27: 0 | L27: 0
A28: 1. Ingresos del proyecto | C28: 918750 | D28: 1323000 | E28: 1543500 | F28: 1764000 | G28: 1984500 | H28: 1984500 | I28: 1984500 | J28: 1984500 | K28: 1984500 | L28: 1984500
A29: Calendario de ingresos (venta del producto)
A30: Concepto | B30: Año 0 | C30: Año 1 | D30: Año 2 | E30: Año 3 | F30: Año 4 | G30: Año 5 | H30: Año 6 | I30: Año 7 | J30: Año 8 | K30: Año 9 | L30: Año 10
A31: Cantidad de camarón (Lb) | C31: 738316.66 | D31: =C31+(C31*D27) -> 1063176 | E31: =D31+(D31*E27) -> 1240372 | F31: =E31+(E31*F27) -> 1417568 | G31: =F31+(F31*G27) -> 1594764 | H31: =G31+(G31*H27) -> 1594764 | I31: =H31+(H31*I27) -> 1594764 | J31: =I31+(I31*J27) -> 1594764 | K31: =J31+(J31*K27) -> 1594764 | L31: =K31+(K31*L27) -> 1594764
A32: Precio unitario de venta ($/Lb) | C32: =C12 -> 3 | D32: =D12 -> 3.21 | E32: =E12 -> 3.4347 | F32: =F12 -> 3.675129 | G32: =G12 -> 3.932388 | H32: =H12 -> 4.2076552 | I32: =I12 -> 4.5021911 | J32: =J12 -> 4.8173444 | ... L32: =L12 -> 5.5153776
A33: Ingresos | C33: =C32*C31 -> 2214950 | D33: =D32*D31 -> 3412794.9 | E33: =E32*E31 -> 4260305.7 | F33: =F32*F31 -> 5209745.2 | G33: =G32*G31 -> 6271230.8 | H33: =H32*H31 -> 6710216.9 | I33: =I32*I31 -> 7179932.1 | J33: =J32*J31 -> 7682527.4 | ... L33: =L32*L31 -> 8795725.6
A35: 2. Costos variables
A36: Calendario de costos variables
A37: Concepto | B37: Año 0 | C37: Año 1 | D37: Año 2 | E37: Año 3 | F37: Año 4 | G37: Año 5 | H37: Año 6 | I37: Año 7 | J37: Año 8 | K37: Año 9 | L37: Año 10
A38: Costos variables | C38: =C15 -> 1332187.5 | D38: =D15 -> 2052634.5 | E38: =E15 -> 2562372.1 | F38: =F15 -> 3133415 | G38: =G15 -> 3771848.3 | H38: =H15 -> 4035877.7 | I38: =I15 -> 4318389.1 | J38: =J15 -> 4620676.3 | ... L38: =L15 -> 5290212.3
A39: Total de costos variables | C39: =C38 -> 1332187.5 | D39: =D38 -> 2052634.5 | E39: =E38 -> 2562372.1 | F39: =F38 -> 3133415 | G39: =G38 -> 3771848.3 | H39: =H38 -> 4035877.7 | I39: =I38 -> 4318389.1 | J39: =J38 -> 4620676.3 | ... L39: =L38 -> 5290212.3
A41: 3. Costos fijos
A42: Calendario de los costos fijos
A43: Concepto | B43: Año 0 | C43: Año 1 | D43: Año 2 | E43: Año 3 | F43: Año 4 | G43: Año 5 | H43: Año 6 | I43: Año 7 | J43: Año 8 | K43: Año 9 | L43: Año 10
A44: Costos fijos de producción | C44: =C16 -> 50000 | D44: =D16 -> 53500 | E44: =E16 -> 57245 | F44: =F16 -> 61252.15 | G44: =G16 -> 65539.8 | H44: =H16 -> 70127.587 | I44: =I16 -> 75036.518 | J44: =J16 -> 80289.074 | ... L44: =L16 -> 91922.961
A45: Gastos administrativos | C45: =C17 -> 200000 | D45: =D17 -> 214000 | E45: =E17 -> 228980 | F45: =F17 -> 245008.6 | G45: =G17 -> 262159.2 | H45: =H17 -> 280510.35 | I45: =I17 -> 300146.07 | J45: =J17 -> 321156.3 | ... L45: =L17 -> 367691.84
A46: Total de costos fijos | C46: =SUM(C44:C45) -> 250000 | D46: =SUM(D44:D45) -> 267500 | E46: =SUM(E44:E45) -> 286225 | F46: =SUM(F44:F45) -> 306260.75 | G46: =SUM(G44:G45) -> 327699 | H46: =SUM(H44:H45) -> 350637.93 | I46: =SUM(I44:I45) -> 375182.59 | J46: =SUM(J44:J45) -> 401445.37 | ... L46: =SUM(L44:L45) -> 459614.8
A48: 4. Capital de trabajo
A49: Capital de trabajo
A50: Necesidad de Efectivo
A51: Concepto | B51: Año 0 | C51: Año 1 | D51: Año 2 | E51: Año 3 | F51: Año 4 | G51: Año 5 | H51: Año 6 | I51: Año 7 | J51: Año 8 | K51: Año 9 | L51: Año 10
A52: Capital de trabajo | C52: =C13+B52 -> 450000 | D52: =D13+C52 -> 700000 | E52: =E13+D52 -> 950000 | F52: =F13+E52 -> 1200000 | G52: =G13+F52 -> 1450000 | H52: =H13+G52 -> 1700000 | I52: =I13+H52 -> 1700000 | J52: =J13+I52 -> 1700000 | ... L52: =L13+K52 -> 1700000
A53: Efectivo requerido en caja | C53: =SUM(C52:C52) -> 450000 | D53: =SUM(D52:D52) -> 700000 | E53: =SUM(E52:E52) -> 950000 | F53: =SUM(F52:F52) -> 1200000 | G53: =SUM(G52:G52) -> 1450000 | H53: =SUM(H52:H52) -> 1700000 | I53: =SUM(I52:I52) -> 1700000 | J53: =SUM(J52:J52) -> 1700000 | ... L53: =SUM(L52:L52) -> 1700000
A55: Cálculo del Capital de Trabajo
A56: Concepto | B56: Cobertura | C56: Año 1 | D56: Año 2 | E56: Año 3 | F56: Año 4 | G56: Año 5 | H56: Año 6 | I56: Año 7 | J56: Año 8 | K56: Año 9 | L56: Año 10
A57: Activo circulante | C57: =C58 -> 450000 | D57: =D58 -> 700000 | E57: =E58 -> 950000 | F57: =F58 -> 1200000 | G57: =G58 -> 1450000 | H57: =H58 -> 1700000 | I57: =I58 -> 1700000 | J57: =J58 -> 1700000 | ... L57: =L58 -> 1700000
A58: Efectivo | C58: =C53 -> 450000 | D58: =D53 -> 700000 | E58: =E53 -> 950000 | F58: =F53 -> 1200000 | G58: =G53 -> 1450000 | H58: =H53 -> 1700000 | I58: =I53 -> 1700000 | J58: =J53 -> 1700000 | ... L58: =L53 -> 1700000
A59: Pasivo circulante | C59: =SUM(C60:C61) -> 0 | D59: =SUM(D60:D61) -> 0 | E59: =SUM(E60:E61) -> 0 | F59: =SUM(F60:F61) -> 0 | G59: =SUM(G60:G61) -> 0 | H59: =SUM(H60:H61) -> 0 | I59: =SUM(I60:I61) -> 0 | J59: =SUM(J60:J61) -> 0 | ... L59: =SUM(L60:L61) -> 0
A60: Cuentas por pagar | C60: 0 | D60: 0 | E60: 0 | F60: 0 | G60: 0 | H60: 0 | I60: 0 | J60: 0 | K60: 0 | L60: 0
A61: Proveedores | C61: 0 | D61: 0 | E61: 0 | F61: 0 | G61: 0 | H61: 0 | I61: 0 | J61: 0 | K61: 0 | L61: 0
A62: Capital de Trabajo (Ac - Pc) | C62: =C57-C59 -> 450000 | D62: =D57-D59 -> 700000 | E62: =E57-E59 -> 950000 | F62: =F57-F59 -> 1200000 | G62: =G57-G59 -> 1450000 | H62: =H57-H59 -> 1700000 | I62: =I57-I59 -> 1700000 | J62: =J57-J59 -> 1700000 | ... L62: =L57-L59 -> 1700000
A63: Incremento Capital Trabajo | B63: =C62-B62 -> 450000 | C63: =D62-C62 -> 250000 | D63: =E62-D62 -> 250000 | E63: =F62-E62 -> 250000 | F63: =G62-F62 -> 250000 | G63: =H62-G62 -> 250000 | H63: =I62-H62 -> 0 | I63: =J62-I62 -> 0 | ... L63: =M62-L62 -> -1700000
A65: 5. Inversiones
A66: Calendario de inversiones
A67: Concepto | B67: Año 0 | C67: Año 1 | D67: Año 2 | E67: Año 3 | F67: Año 4 | G67: Año 5 | H67: Año 6 | I67: Año 7 | J67: Año 8 | K67: Año 9 | L67: Año 10
A68: Activos Fijos
A69: Inversiones a 20 años | B69: 100000
A70: Inversiones a 10 años | B70: =3000000+200000+450000+50000 -> 3700000
A71: Inversiones a 5 años | B71: =300000+100000 -> 400000
A72: Inversion terrenos | B72: 750000
A73: Gastos Pre-operativos
A74: Gastos puesta en marcha | B74: 0
A75: Capital de trabajo
A76: Capital de trabajo | B76: =B63 -> 450000 | C76: =C63 -> 250000 | D76: =D63 -> 250000 | E76: =E63 -> 250000 | F76: =F63 -> 250000 | G76: =G63 -> 250000 | H76: =H63 -> 0 | I76: =I63 -> 0 | ... L76: =L63 -> -1700000
A77: Total Inversiones | B77: =SUM(B68:B76) -> 5400000 | C77: =SUM(C68:C76) -> 250000 | D77: =SUM(D68:D76) -> 250000 | E77: =SUM(E68:E76) -> 250000 | F77: =SUM(F68:F76) -> 250000 | G77: =SUM(G68:G76) -> 250000 | H77: =SUM(H68:H76) -> 0 | I77: =SUM(I68:I76) -> 0 | ... L77: =SUM(L68:L76) -> -1700000
A79: 6. Depreciaciones y Amortizaciones
A80: Calendario de Depreciaciones y Amortizaciones
A81: Concepto | B81: Año 0 | C81: Año 1 | D81: Año 2 | E81: Año 3 | F81: Año 4 | G81: Año 5 | H81: Año 6 | I81: Año 7 | J81: Año 8 | K81: Año 9 | L81: Año 10 | R81: Inversión | S81: Valor Activo | T81: Valor residual | U81: Vida útil | V81: Dep. Anual
A82: Inversiones a 20 años | C82: =$V$82 -> 2500 | D82: =$V$82 -> 2500 | E82: =$V$82 -> 2500 | F82: =$V$82 -> 2500 | G82: =$V$82 -> 2500 | H82: =$V$82 -> 2500 | I82: =$V$82 -> 2500 | J82: =$V$82 -> 2500 | ... L82: =$V$82 -> 2500 | R82: Edificio | S82: =B69 -> 100000 | T82: 50000 | U82: 20 | V82: =(S82-T82)/U82 -> 2500
A83: Inversiones a 10 años | C83: =$V$83+$V$84 -> 270000 | D83: =$V$83+$V$84 -> 270000 | E83: =$V$83+$V$84 -> 270000 | F83: =$V$83+$V$84 -> 270000 | G83: =$V$83+$V$84 -> 270000 | H83: =$V$83+$V$84 -> 270000 | I83: =$V$83+$V$84 -> 270000 | J83: =$V$83+$V$84 -> 270000 | ... L83: =$V$83+$V$84 -> 270000 | R83: Estanque y canales | S83: 3000000 | T83: 1000000 | U83: 10 | V83: =(S83-T83)/U83 -> 200000
A84: Inversiones a 5 años | C84: =$V$85 -> 80000 | D84: =$V$85 -> 80000 | E84: =$V$85 -> 80000 | F84: =$V$85 -> 80000 | G84: =$V$85 -> 80000 | H84: 0 | I84: 0 | J84: 0 | K84: 0 | L84: 0 | R84: Maq & Equipo | S84: =B70-S83 -> 700000 | T84: 0 | U84: 10 | V84: =(S84-T84)/U84 -> 70000
A85: Total Depreciación | C85: =SUM(C82:C84) -> 352500 | D85: =SUM(D82:D84) -> 352500 | E85: =SUM(E82:E84) -> 352500 | F85: =SUM(F82:F84) -> 352500 | G85: =SUM(G82:G84) -> 352500 | H85: =SUM(H82:H84) -> 272500 | I85: =SUM(I82:I84) -> 272500 | J85: =SUM(J82:J84) -> 272500 | ... L85: =SUM(L82:L84) -> 272500 | R85: Vehículos y embarcaciones | S85: =B71 -> 400000 | T85: 0 | U85: 5 | V85: =(S85-T85)/U85 -> 80000
S86: =SUM(S82:S85) -> 4200000
A87: Amortización pre-operativos | C87: =$B$74/10 -> 0 | D87: =$B$74/10 -> 0 | E87: =$B$74/10 -> 0 | F87: =$B$74/10 -> 0 | G87: =$B$74/10 -> 0 | H87: =$B$74/10 -> 0 | I87: =$B$74/10 -> 0 | J87: =$B$74/10 -> 0 | ... L87: =$B$74/10 -> 0
A88: Total Amortización | C88: =SUM(C87) -> 0 | D88: =SUM(D87) -> 0 | E88: =SUM(E87) -> 0 | F88: =SUM(F87) -> 0 | G88: =SUM(G87) -> 0 | H88: =SUM(H87) -> 0 | I88: =SUM(I87) -> 0 | J88: =SUM(J87) -> 0 | ... L88: =SUM(L87) -> 0
A90: 7. Valor de desecho del proyecto
A91: Clalculo del valor de desecho del proyecto (método contable)
A92: Concepto | B92: Valor del | C92: Depreciación por periodo | M92: Valor de
B93: Activo | C93: Año 1 | D93: Año 2 | E93: Año 3 | F93: Año 4 | G93: Año 5 | H93: Año 6 | I93: Año 7 | J93: Año 8 | K93: Año 9 | L93: Año 10 | M93: Desecho
A94: Inversiones a 20 años | B94: =B69 -> 100000 | C94: =C82 -> 2500 | D94: =D82 -> 2500 | E94: =E82 -> 2500 | F94: =F82 -> 2500 | G94: =G82 -> 2500 | H94: =H82 -> 2500 | I94: =I82 -> 2500 | J94: =J82 -> 2500 | ... L94: =L82 -> 2500 | M94: =B94-SUM(C94:L94) -> 75000
A95: Inversiones a 10 años | B95: =B70 -> 3700000 | C95: =C83 -> 270000 | D95: =D83 -> 270000 | E95: =E83 -> 270000 | F95: =F83 -> 270000 | G95: =G83 -> 270000 | H95: =H83 -> 270000 | I95: =I83 -> 270000 | J95: =J83 -> 270000 | ... L95: =L83 -> 270000 | M95: =B95-SUM(C95:L95) -> 1000000
A96: Inversiones a 5 años | B96: =B71 -> 400000 | C96: =C84 -> 80000 | D96: =D84 -> 80000 | E96: =E84 -> 80000 | F96: =F84 -> 80000 | G96: =G84 -> 80000 | H96: =H84 -> 0 | I96: =I84 -> 0 | J96: =J84 -> 0 | ... L96: =L84 -> 0 | M96: =B96-SUM(C96:L96) -> 0
A97: Amortización pre-operativos | B97: =B74 -> 0 | C97: =C87 -> 0 | D97: =D87 -> 0 | E97: =E87 -> 0 | F97: =F87 -> 0 | G97: =G87 -> 0 | H97: =H87 -> 0 | I97: =I87 -> 0 | J97: =J87 -> 0 | ... L97: =L87 -> 0 | M97: =B97-SUM(C97:L97) -> 0
A98: Valor de desecho total | M98: =SUM(M94:M97) -> 1075000
A100: 8. Financiamiento
A101: Cálculo del Financiamiento
A102: Financiamiento bancario (valor) | B102: =B77*E102 -> 0 | E102: 0
A103: Financiamiento bancario (tasa) | B103: =B22 -> 0.1
A104: Financiamiento bancario (periodos) | B104: 7 | C104: años
A105: Modalidad | B105: Pagos exactos
A107: Concepto | B107: Año 0 | C107: Año 1 | D107: Año 2 | E107: Año 3 | F107: Año 4 | G107: Año 5 | H107: Año 6 | I107: Año 7
A108: Saldo crédito | B108: =B102 -> 0 | C108: =B108-C111 -> 0 | D108: =C108-D111 -> 0 | E108: =D108-E111 -> 0 | F108: =E108-F111 -> 0 | G108: =F108-G111 -> 0 | H108: =G108-H111 -> 0 | I108: =H108-I111 -> 0
A109: Cuota mensual (anualidad) | C109: =C110 -> 0 | D109: =D110 -> 0 | E109: 0 | F109: 0 | G109: 0 | H109: 0 | I109: =(H108*B103)+H108 -> 0
A110: Intereses | C110: =B108*$B$103 -> 0 | D110: =C108*$B$103 -> 0 | E110: =D108*$B$103 -> 0 | F110: =E108*$B$103 -> 0 | G110: =F108*$B$103 -> 0 | H110: =G108*$B$103 -> 0 | I110: =H108*$B$103 -> 0
A111: Abono a capital (amortización) | C111: =C109-C110 -> 0 | D111: =D109-D110 -> 0 | E111: =E109-E110 -> 0 | F111: =F109-F110 -> 0 | G111: =G109-G110 -> 0 | H111: =H109-H110 -> 0 | I111: =I109-I110 -> 0
...

Sheet Francés
A1: Camaronera Industrial
A3: Variables
A4: Horizonte de evaluación (años) | B4: 10
A5: Devaluación | B5: 0.05
A6: Inflación | B6: 0.07
B7: Año 0 | C7: Año 1 | D7: Año 2 | E7: Año 3 | F7: Año 4 | G7: Año 5 | H7: Año 6 | I7: Año 7 | J7: Año 8 | K7: Año 9 | L7: Año 10
A8: Área en producción (Ha) | C8: 750 | D8: 900 | E8: 900 | F8: 900 | G8: 900 | H8: 900 | I8: 900 | J8: 900 | K8: 900 | L8: 900
A9: Producción neta (Lb/Ha/año) | C9: =1225 -> 1225 | D9: =1470 -> 1470 | E9: =1715 -> 1715 | F9: =1960 -> 1960 | G9: =2205 -> 2205 | H9: =2205 -> 2205 | I9: =2205 -> 2205 | J9: =2205 -> 2205 | K9: =2205 -> 2205 | L9: =2205 -> 2205
A10: Producción neta total (Lb/año) | C10: =C9*C8 -> 918750 | D10: =D9*D8 -> 1323000 | E10: =E9*E8 -> 1543500 | F10: =F9*F8 -> 1764000 | G10: =G9*G8 -> 1984500 | H10: =H9*H8 -> 1984500 | I10: =I9*I8 -> 1984500 | J10: =J9*J8 -> 1984500 | ... L10: =L9*L8 -> 1984500
A11: Tasa de cambio | C11: 1 | D11: =C11+(C11*$B$5) -> 1.05 | E11: =D11+(D11*$B$5) -> 1.1025 | F11: =E11+(E11*$B$5) -> 1.157625 | G11: =F11+(F11*$B$5) -> 1.2155063 | H11: =G11+(G11*$B$5) -> 1.2762816 | I11: =H11+(H11*$B$5) -> 1.3400956 | J11: =I11+(I11*$B$5) -> 1.4071004 | K11: =J11+(J11*$B$5) -> 1.4774554 | L11: =K11+(K11*$B$5) -> 1.5513282
A12: Precio de venta FOB ($/Lb) | C12: 3 | D12: =C12+(C12*$B$6) -> 3.21 | E12: =D12+(D12*$B$6) -> 3.4347 | F12: =E12+(E12*$B$6) -> 3.675129 | G12: =F12+(F12*$B$6) -> 3.932388 | H12: =G12+(G12*$B$6) -> 4.2076552 | I12: =H12+(H12*$B$6) -> 4.5021911 | J12: =I12+(I12*$B$6) -> 4.8173444 | K12: =J12+(J12*$B$6) -> 5.1545585 | L12: =K12+(K12*$B$6) -> 5.5153776
A13: Capital de trabajo | C13: 450000 | D13: 250000 | E13: 250000 | F13: 250000 | G13: 250000 | H13: 250000 | I13: 0 | J13: 0 | K13: 0 | L13: 0
A14: Costos variables ($1.45 x Lb) | C14: =1.45 -> 1.45 | D14: =C14+(C14*$B$6) -> 1.5515 | E14: =D14+(D14*$B$6) -> 1.660105 | F14: =E14+(E14*$B$6) -> 1.7763123 | G14: =F14+(F14*$B$6) -> 1.9006542 | H14: =G14+(G14*$B$6) -> 2.0337 | I14: =H14+(H14*$B$6) -> 2.176059 | J14: =I14+(I14*$B$6) -> 2.3283831 | K14: =J14+(J14*$B$6) -> 2.49137 | L14: =K14+(K14*$B$6) -> 2.6657659
A15: Costos variables anuales | C15: =C14*C10 -> 1332187.5 | D15: =D14*D10 -> 2052634.5 | E15: =E14*E10 -> 2562372.1 | F15: =F14*F10 -> 3133415 | G15: =G14*G10 -> 3771848.3 | H15: =H14*H10 -> 4035877.7 | I15: =I14*I10 -> 4318389.1 | J15: =J14*J10 -> 4620676.3 | ... L15: =L14*L10 -> 5290212.3
A16: Costos fijos de producción | C16: 50000 | D16: =C16+(C16*$B$6) -> 53500 | E16: =D16+(D16*$B$6) -> 57245 | F16: =E16+(E16*$B$6) -> 61252.15 | G16: =F16+(F16*$B$6) -> 65539.8 | H16: =G16+(G16*$B$6) -> 70127.587 | I16: =H16+(H16*$B$6) -> 75036.518 | J16: =I16+(I16*$B$6) -> 80289.074 | K16: =J16+(J16*$B$6) -> 85909.309 | L16: =K16+(K16*$B$6) -> 91922.961
A17: Gastos administrativos | C17: 200000 | D17: =C17+(C17*$B$6) -> 214000 | E17: =D17+(D17*$B$6) -> 228980 | F17: =E17+(E17*$B$6) -> 245008.6 | G17: =F17+(F17*$B$6) -> 262159.2 | H17: =G17+(G17*$B$6) -> 280510.35 | I17: =H17+(H17*$B$6) -> 300146.07 | J17: =I17+(I17*$B$6) -> 321156.3 | K17: =J17+(J17*$B$6) -> 343637.24 | L17: =K17+(K17*$B$6) -> 367691.84
A19: Valor residual del terreno | B19: 1250000
A20: Valor residual de estanques y canales | B20: 1000000
A21: Valor residual de edificios | B21: 50000
A22: Tasa de fiananciamiento bancario | B22: 0.1
A23: Plazo del financiamiento bancario (años) | B23: 7
A24: Plazo del financiamiento bancario (valor) | B24: =5400000*0.5 -> 2700000
A25: Tasa de corte | B25: 0.19
A26: Tasa de ISR | B26: 0.3
A28: 1. Ingresos del proyecto
A29: Calendario de ingresos (venta del producto)
A30: Concepto | B30: Año 0 | C30: Año 1 | D30: Año 2 | E30: Año 3 | F30: Año 4 | G30: Año 5 | H30: Año 6 | I30: Año 7 | J30: Año 8 | K30: Año 9 | L30: Año 10
A31: Cantidad de camarón (Lb) | C31: =C10 -> 918750 | D31: =D10 -> 1323000 | E31: =E10 -> 1543500 | F31: =F10 -> 1764000 | G31: =G10 -> 1984500 | H31: =H10 -> 1984500 | I31: =I10 -> 1984500 | J31: =J10 -> 1984500 | ... L31: =L10 -> 1984500
A32: Precio unitario de venta ($/Lb) | C32: =C12 -> 3 | D32: =D12 -> 3.21 | E32: =E12 -> 3.4347 | F32: =F12 -> 3.675129 | G32: =G12 -> 3.932388 | H32: =H12 -> 4.2076552 | I32: =I12 -> 4.5021911 | J32: =J12 -> 4.8173444 | ... L32: =L12 -> 5.5153776
A33: Ingresos | C33: =C32*C31 -> 2756250 | D33: =D32*D31 -> 4246830 | E33: =E32*E31 -> 5301459.5 | F33: =F32*F31 -> 6482927.6 | G33: =G32*G31 -> 7803824 | H33: =H32*H31 -> 8350091.7 | I33: =I32*I31 -> 8934598.1 | J33: =J32*J31 -> 9560020 | ... L33: =L32*L31 -> 10945267
A35: 2. Costos variables
A36: Calendario de costos variables
A37: Concepto | B37: Año 0 | C37: Año 1 | D37: Año 2 | E37: Año 3 | F37: Año 4 | G37: Año 5 | H37: Año 6 | I37: Año 7 | J37: Año 8 | K37: Año 9 | L37: Año 10
A38: Costos variables | C38: =C15 -> 1332187.5 | D38: =D15 -> 2052634.5 | E38: =E15 -> 2562372.1 | F38: =F15 -> 3133415 | G38: =G15 -> 3771848.3 | H38: =H15 -> 4035877.7 | I38: =I15 -> 4318389.1 | J38: =J15 -> 4620676.3 | ... L38: =L15 -> 5290212.3
A39: Total de costos variables | C39: =C38 -> 1332187.5 | D39: =D38 -> 2052634.5 | E39: =E38 -> 2562372.1 | F39: =F38 -> 3133415 | G39: =G38 -> 3771848.3 | H39: =H38 -> 4035877.7 | I39: =I38 -> 4318389.1 | J39: =J38 -> 4620676.3 | ... L39: =L38 -> 5290212.3
A41: 3. Costos fijos
A42: Calendario de los costos fijos
A43: Concepto | B43: Año 0 | C43: Año 1 | D43: Año 2 | E43: Año 3 | F43: Año 4 | G43: Año 5 | H43: Año 6 | I43: Año 7 | J43: Año 8 | K43: Año 9 | L43: Año 10
A44: Costos fijos de producción | C44: =C16 -> 50000 | D44: =D16 -> 53500 | E44: =E16 -> 57245 | F44: =F16 -> 61252.15 | G44: =G16 -> 65539.8 | H44: =H16 -> 70127.587 | I44: =I16 -> 75036.518 | J44: =J16 -> 80289.074 | ... L44: =L16 -> 91922.961
A45: Gastos administrativos | C45: =C17 -> 200000 | D45: =D17 -> 214000 | E45: =E17 -> 228980 | F45: =F17 -> 245008.6 | G45: =G17 -> 262159.2 | H45: =H17 -> 280510.35 | I45: =I17 -> 300146.07 | J45: =J17 -> 321156.3 | ... L45: =L17 -> 367691.84
A46: Total de costos fijos | C46: =SUM(C44:C45) -> 250000 | D46: =SUM(D44:D45) -> 267500 | E46: =SUM(E44:E45) -> 286225 | F46: =SUM(F44:F45) -> 306260.75 | G46: =SUM(G44:G45) -> 327699 | H46: =SUM(H44:H45) -> 350637.93 | I46: =SUM(I44:I45) -> 375182.59 | J46: =SUM(J44:J45) -> 401445.37 | ... L46: =SUM(L44:L45) -> 459614.8
A48: 4. Capital de trabajo
A49: Capital de trabajo
A50: Necesidad de Efectivo
A51: Concepto | B51: Año 0 | C51: Año 1 | D51: Año 2 | E51: Año 3 | F51: Año 4 | G51: Año 5 | H51: Año 6 | I51: Año 7 | J51: Año 8 | K51: Año 9 | L51: Año 10
A52: Capital de trabajo | C52: =C13+B52 -> 450000 | D52: =D13+C52 -> 700000 | E52: =E13+D52 -> 950000 | F52: =F13+E52 -> 1200000 | G52: =G13+F52 -> 1450000 | H52: =H13+G52 -> 1700000 | I52: =I13+H52 -> 1700000 | J52: =J13+I52 -> 1700000 | ... L52: =L13+K52 -> 1700000
A53: Efectivo requerido en caja | C53: =SUM(C52:C52) -> 450000 | D53: =SUM(D52:D52) -> 700000 | E53: =SUM(E52:E52) -> 950000 | F53: =SUM(F52:F52) -> 1200000 | G53: =SUM(G52:G52) -> 1450000 | H53: =SUM(H52:H52) -> 1700000 | I53: =SUM(I52:I52) -> 1700000 | J53: =SUM(J52:J52) -> 1700000 | ... L53: =SUM(L52:L52) -> 1700000
A55: Cálculo del Capital de Trabajo
A56: Concepto | B56: Cobertura | C56: Año 1 | D56: Año 2 | E56: Año 3 | F56: Año 4 | G56: Año 5 | H56: Año 6 | I56: Año 7 | J56: Año 8 | K56: Año 9 | L56: Año 10
A57: Activo circulante | C57: =C58 -> 450000 | D57: =D58 -> 700000 | E57: =E58 -> 950000 | F57: =F58 -> 1200000 | G57: =G58 -> 1450000 | H57: =H58 -> 1700000 | I57: =I58 -> 1700000 | J57: =J58 -> 1700000 | ... L57: =L58 -> 1700000
A58: Efectivo | C58: =C53 -> 450000 | D58: =D53 -> 700000 | E58: =E53 -> 950000 | F58: =F53 -> 1200000 | G58: =G53 -> 1450000 | H58: =H53 -> 1700000 | I58: =I53 -> 1700000 | J58: =J53 -> 1700000 | ... L58: =L53 -> 1700000
A59: Pasivo circulante | C59: =SUM(C60:C61) -> 0 | D59: =SUM(D60:D61) -> 0 | E59: =SUM(E60:E61) -> 0 | F59: =SUM(F60:F61) -> 0 | G59: =SUM(G60:G61) -> 0 | H59: =SUM(H60:H61) -> 0 | I59: =SUM(I60:I61) -> 0 | J59: =SUM(J60:J61) -> 0 | ... L59: =SUM(L60:L61) -> 0
A60: Cuentas por pagar | C60: 0 | D60: 0 | E60: 0 | F60: 0 | G60: 0 | H60: 0 | I60: 0 | J60: 0 | K60: 0 | L60: 0
A61: Proveedores | C61: 0 | D61: 0 | E61: 0 | F61: 0 | G61: 0 | H61: 0 | I61: 0 | J61: 0 | K61: 0 | L61: 0
A62: Capital de Trabajo (Ac - Pc) | C62: =C57-C59 -> 450000 | D62: =D57-D59 -> 700000 | E62: =E57-E59 -> 950000 | F62: =F57-F59 -> 1200000 | G62: =G57-G59 -> 1450000 | H62: =H57-H59 -> 1700000 | I62: =I57-I59 -> 1700000 | J62: =J57-J59 -> 1700000 | ... L62: =L57-L59 -> 1700000
A63: Incremento Capital Trabajo | B63: =C62-B62 -> 450000 | C63: =D62-C62 -> 250000 | D63: =E62-D62 -> 250000 | E63: =F62-E62 -> 250000 | F63: =G62-F62 -> 250000 | G63: =H62-G62 -> 250000 | H63: =I62-H62 -> 0 | I63: =J62-I62 -> 0 | ... L63: =M62-L62 -> -1700000
A65: 5. Inversiones
A66: Calendario de inversiones
A67: Concepto | B67: Año 0 | C67: Año 1 | D67: Año 2 | E67: Año 3 | F67: Año 4 | G67: Año 5 | H67: Año 6 | I67: Año 7 | J67: Año 8 | K67: Año 9 | L67: Año 10
A68: Activos Fijos
A69: Inversiones a 20 años | B69: 100000
A70: Inversiones a 10 años | B70: =3000000+200000+450000+50000 -> 3700000
A71: Inversiones a 5 años | B71: =300000+100000 -> 400000
A72: Inversion terrenos | B72: 750000
A73: Gastos Pre-operativos
A74: Gastos puesta en marcha | B74: 0
A75: Capital de trabajo
A76: Capital de trabajo | B76: =B63 -> 450000 | C76: =C63 -> 250000 | D76: =D63 -> 250000 | E76: =E63 -> 250000 | F76: =F63 -> 250000 | G76: =G63 -> 250000 | H76: =H63 -> 0 | I76: =I63 -> 0 | ... L76: =L63 -> -1700000
A77: Total Inversiones | B77: =SUM(B68:B76) -> 5400000 | C77: =SUM(C68:C76) -> 250000 | D77: =SUM(D68:D76) -> 250000 | E77: =SUM(E68:E76) -> 250000 | F77: =SUM(F68:F76) -> 250000 | G77: =SUM(G68:G76) -> 250000 | H77: =SUM(H68:H76) -> 0 | I77: =SUM(I68:I76) -> 0 | ... L77: =SUM(L68:L76) -> -1700000
A79: 6. Depreciaciones y Amortizaciones
A80: Calendario de Depreciaciones y Amortizaciones
A81: Concepto | B81: Año 0 | C81: Año 1 | D81: Año 2 | E81: Año 3 | F81: Año 4 | G81: Año 5 | H81: Año 6 | I81: Año 7 | J81: Año 8 | K81: Año 9 | L81: Año 10 | R81: Inversión | S81: Valor Activo | T81: Valor residual | U81: Vida útil | V81: Dep. Anual
A82: Inversiones a 20 años | C82: =$V$82 -> 2500 | D82: =$V$82 -> 2500 | E82: =$V$82 -> 2500 | F82: =$V$82 -> 2500 | G82: =$V$82 -> 2500 | H82: =$V$82 -> 2500 | I82: =$V$82 -> 2500 | J82: =$V$82 -> 2500 | ... L82: =$V$82 -> 2500 | R82: Edificio | S82: =B69 -> 100000 | T82: 50000 | U82: 20 | V82: =(S82-T82)/U82 -> 2500
A83: Inversiones a 10 años | C83: =$V$83+$V$84 -> 270000 | D83: =$V$83+$V$84 -> 270000 | E83: =$V$83+$V$84 -> 270000 | F83: =$V$83+$V$84 -> 270000 | G83: =$V$83+$V$84 -> 270000 | H83: =$V$83+$V$84 -> 270000 | I83: =$V$83+$V$84 -> 270000 | J83: =$V$83+$V$84 -> 270000 | ... L83: =$V$83+$V$84 -> 270000 | R83: Estanque y canales | S83: 3000000 | T83: 1000000 | U83: 10 | V83: =(S83-T83)/U83 -> 200000
A84: Inversiones a 5 años | C84: =$V$85 -> 80000 | D84: =$V$85 -> 80000 | E84: =$V$85 -> 80000 | F84: =$V$85 -> 80000 | G84: =$V$85 -> 80000 | H84: 0 | I84: 0 | J84: 0 | K84: 0 | L84: 0 | R84: Maq & Equipo | S84: =B70-S83 -> 700000 | T84: 0 | U84: 10 | V84: =(S84-T84)/U84 -> 70000
A85: Total Depreciación | C85: =SUM(C82:C84) -> 352500 | D85: =SUM(D82:D84) -> 352500 | E85: =SUM(E82:E84) -> 352500 | F85: =SUM(F82:F84) -> 352500 | G85: =SUM(G82:G84) -> 352500 | H85: =SUM(H82:H84) -> 272500 | I85: =SUM(I82:I84) -> 272500 | J85: =SUM(J82:J84) -> 272500 | ... L85: =SUM(L82:L84) -> 272500 | R85: Vehículos y embarcaciones | S85: =B71 -> 400000 | T85: 0 | U85: 5 | V85: =(S85-T85)/U85 -> 80000
S86: =SUM(S82:S85) -> 4200000
A87: Amortización pre-operativos | C87: =$B$74/10 -> 0 | D87: =$B$74/10 -> 0 | E87: =$B$74/10 -> 0 | F87: =$B$74/10 -> 0 | G87: =$B$74/10 -> 0 | H87: =$B$74/10 -> 0 | I87: =$B$74/10 -> 0 | J87: =$B$74/10 -> 0 | ... L87: =$B$74/10 -> 0
A88: Total Amortización | C88: =SUM(C87) -> 0 | D88: =SUM(D87) -> 0 | E88: =SUM(E87) -> 0 | F88: =SUM(F87) -> 0 | G88: =SUM(G87) -> 0 | H88: =SUM(H87) -> 0 | I88: =SUM(I87) -> 0 | J88: =SUM(J87) -> 0 | ... L88: =SUM(L87) -> 0
A90: 7. Valor de desecho del proyecto
A91: Clalculo del valor de desecho del proyecto (método contable)
A92: Concepto | B92: Valor del | C92: Depreciación por periodo | M92: Valor de
B93: Activo | C93: Año 1 | D93: Año 2 | E93: Año 3 | F93: Año 4 | G93: Año 5 | H93: Año 6 | I93: Año 7 | J93: Año 8 | K93: Año 9 | L93: Año 10 | M93: Desecho
A94: Inversiones a 20 años | B94: =B69 -> 100000 | C94: =C82 -> 2500 | D94: =D82 -> 2500 | E94: =E82 -> 2500 | F94: =F82 -> 2500 | G94: =G82 -> 2500 | H94: =H82 -> 2500 | I94: =I82 -> 2500 | J94: =J82 -> 2500 | ... L94: =L82 -> 2500 | M94: =B94-SUM(C94:L94) -> 75000
A95: Inversiones a 10 años | B95: =B70 -> 3700000 | C95: =C83 -> 270000 | D95: =D83 -> 270000 | E95: =E83 -> 270000 | F95: =F83 -> 270000 | G95: =G83 -> 270000 | H95: =H83 -> 270000 | I95: =I83 -> 270000 | J95: =J83 -> 270000 | ... L95: =L83 -> 270000 | M95: =B95-SUM(C95:L95) -> 1000000
A96: Inversiones a 5 años | B96: =B71 -> 400000 | C96: =C84 -> 80000 | D96: =D84 -> 80000 | E96: =E84 -> 80000 | F96: =F84 -> 80000 | G96: =G84 -> 80000 | H96: =H84 -> 0 | I96: =I84 -> 0 | J96: =J84 -> 0 | ... L96: =L84 -> 0 | M96: =B96-SUM(C96:L96) -> 0
A97: Amortización pre-operativos | B97: =B74 -> 0 | C97: =C87 -> 0 | D97: =D87 -> 0 | E97: =E87 -> 0 | F97: =F87 -> 0 | G97: =G87 -> 0 | H97: =H87 -> 0 | I97: =I87 -> 0 | J97: =J87 -> 0 | ... L97: =L87 -> 0 | M97: =B97-SUM(C97:L97) -> 0
A98: Valor de desecho total | M98: =SUM(M94:M97) -> 1075000
A100: 8. Financiamiento
A101: Cálculo del Financiamiento
A102: Financiamiento bancario (valor) | B102: =B77*E102 -> 2700000 | E102: 0.5
A103: Financiamiento bancario (tasa) | B103: =B22 -> 0.1
A104: Financiamiento bancario (periodos) | B104: 7 | C104: años
A105: Modalidad | B105: Pagos exactos
A107: Concepto | B107: Año 0 | C107: Año 1 | D107: Año 2 | E107: Año 3 | F107: Año 4 | G107: Año 5 | H107: Año 6 | I107: Año 7
A108: Saldo crédito | B108: =B102 -> 2700000 | C108: =B108-C111 -> 2700000 | D108: =C108-D111 -> 2700000 | E108: =D108-E111 -> 2257746.8 | F108: =E108-F111 -> 1771268.3 | G108: =F108-G111 -> 1236141.9 | H108: =G108-H111 -> 647502.91 | I108: =H108-I111 -> 0
A109: Cuota mensual (anualidad) | C109: =C110 -> 270000 | D109: =D110 -> 270000 | E109: =PMT($B$103,5,-$B$102) -> 712253.2 | F109: =PMT($B$103,5,-$B$102) -> 712253.2 | G109: =PMT($B$103,5,-$B$102) -> 712253.2 | H109: =PMT($B$103,5,-$B$102) -> 712253.2 | I109: =PMT($B$103,5,-$B$102) -> 712253.2
A110: Intereses | C110: =B108*$B$103 -> 270000 | D110: =C108*$B$103 -> 270000 | E110: =D108*$B$103 -> 270000 | F110: =E108*$B$103 -> 225774.68 | G110: =F108*$B$103 -> 177126.83 | H110: =G108*$B$103 -> 123614.19 | I110: =H108*$B$103 -> 64750.291
A111: Abono a capital (amortización) | C111: =C109-C110 -> 0 | D111: =D109-D110 -> 0 | E111: =E109-E110 -> 442253.2 | F111: =F109-F110 -> 486478.52 | G111: =G109-G110 -> 535126.37 | H111: =H109-H110 -> 588639.01 | I111: =I109-I110 -> 647502.91
A113: 9.Flujo de caja del proyecto
...

Sheet Americano
A1: Camaronera Industrial
A3: Variables
A4: Horizonte de evaluación (años) | B4: 10
A5: Devaluación | B5: 0.05
A6: Inflación | B6: 0.07
B7: Año 0 | C7: Año 1 | D7: Año 2 | E7: Año 3 | F7: Año 4 | G7: Año 5 | H7: Año 6 | I7: Año 7 | J7: Año 8 | K7: Año 9 | L7: Año 10
A8: Área en producción (Ha) | C8: 750 | D8: 900 | E8: 900 | F8: 900 | G8: 900 | H8: 900 | I8: 900 | J8: 900 | K8: 900 | L8: 900
A9: Producción neta (Lb/Ha/año) | C9: =1225 -> 1225 | D9: =1470 -> 1470 | E9: =1715 -> 1715 | F9: =1960 -> 1960 | G9: =2205 -> 2205 | H9: =2205 -> 2205 | I9: =2205 -> 2205 | J9: =2205 -> 2205 | K9: =2205 -> 2205 | L9: =2205 -> 2205
A10: Producción neta total (Lb/año) | C10: =C9*C8 -> 918750 | D10: =D9*D8 -> 1323000 | E10: =E9*E8 -> 1543500 | F10: =F9*F8 -> 1764000 | G10: =G9*G8 -> 1984500 | H10: =H9*H8 -> 1984500 | I10: =I9*I8 -> 1984500 | J10: =J9*J8 -> 1984500 | ... L10: =L9*L8 -> 1984500
A11: Tasa de cambio | C11: 1 | D11: =C11+(C11*$B$5) -> 1.05 | E11: =D11+(D11*$B$5) -> 1.1025 | F11: =E11+(E11*$B$5) -> 1.157625 | G11: =F11+(F11*$B$5) -> 1.2155063 | H11: =G11+(G11*$B$5) -> 1.2762816 | I11: =H11+(H11*$B$5) -> 1.3400956 | J11: =I11+(I11*$B$5) -> 1.4071004 | K11: =J11+(J11*$B$5) -> 1.4774554 | L11: =K11+(K11*$B$5) -> 1.5513282
A12: Precio de venta FOB ($/Lb) | C12: 3 | D12: =C12+(C12*$B$6) -> 3.21 | E12: =D12+(D12*$B$6) -> 3.4347 | F12: =E12+(E12*$B$6) -> 3.675129 | G12: =F12+(F12*$B$6) -> 3.932388 | H12: =G12+(G12*$B$6) -> 4.2076552 | I12: =H12+(H12*$B$6) -> 4.5021911 | J12: =I12+(I12*$B$6) -> 4.8173444 | K12: =J12+(J12*$B$6) -> 5.1545585 | L12: =K12+(K12*$B$6) -> 5.5153776
A13: Capital de trabajo | C13: 450000 | D13: 250000 | E13: 250000 | F13: 250000 | G13: 250000 | H13: 250000 | I13: 0 | J13: 0 | K13: 0 | L13: 0
A14: Costos variables ($1.45 x Lb) | C14: =1.45 -> 1.45 | D14: =C14+(C14*$B$6) -> 1.5515 | E14: =D14+(D14*$B$6) -> 1.660105 | F14: =E14+(E14*$B$6) -> 1.7763123 | G14: =F14+(F14*$B$6) -> 1.9006542 | H14: =G14+(G14*$B$6) -> 2.0337 | I14: =H14+(H14*$B$6) -> 2.176059 | J14: =I14+(I14*$B$6) -> 2.3283831 | K14: =J14+(J14*$B$6) -> 2.49137 | L14: =K14+(K14*$B$6) -> 2.6657659
A15: Costos variables anuales | C15: =C14*C10 -> 1332187.5 | D15: =D14*D10 -> 2052634.5 | E15: =E14*E10 -> 2562372.1 | F15: =F14*F10 -> 3133415 | G15: =G14*G10 -> 3771848.3 | H15: =H14*H10 -> 4035877.7 | I15: =I14*I10 -> 4318389.1 | J15: =J14*J10 -> 4620676.3 | ... L15: =L14*L10 -> 5290212.3
A16: Costos fijos de producción | C16: 50000 | D16: =C16+(C16*$B$6) -> 53500 | E16: =D16+(D16*$B$6) -> 57245 | F16: =E16+(E16*$B$6) -> 61252.15 | G16: =F16+(F16*$B$6) -> 65539.8 | H16: =G16+(G16*$B$6) -> 70127.587 | I16: =H16+(H16*$B$6) -> 75036.518 | J16: =I16+(I16*$B$6) -> 80289.074 | K16: =J16+(J16*$B$6) -> 85909.309 | L16: =K16+(K16*$B$6) -> 91922.961
A17: Gastos administrativos | C17: 200000 | D17: =C17+(C17*$B$6) -> 214000 | E17: =D17+(D17*$B$6) -> 228980 | F17: =E17+(E17*$B$6) -> 245008.6 | G17: =F17+(F17*$B$6) -> 262159.2 | H17: =G17+(G17*$B$6) -> 280510.35 | I17: =H17+(H17*$B$6) -> 300146.07 | J17: =I17+(I17*$B$6) -> 321156.3 | K17: =J17+(J17*$B$6) -> 343637.24 | L17: =K17+(K17*$B$6) -> 367691.84
A19: Valor residual del terreno | B19: 1250000
A20: Valor residual de estanques y canales | B20: 1000000
A21: Valor residual de edificios | B21: 50000
A22: Tasa de fiananciamiento bancario | B22: 0.1
A23: Plazo del financiamiento bancario (años) | B23: 7
A24: Plazo del financiamiento bancario (valor) | B24: =5400000*0.5 -> 2700000
A25: Tasa de corte | B25: 0.19
A26: Tasa de ISR | B26: 0.3
A28: 1. Ingresos del proyecto
A29: Calendario de ingresos (venta del producto)
A30: Concepto | B30: Año 0 | C30: Año 1 | D30: Año 2 | E30: Año 3 | F30: Año 4 | G30: Año 5 | H30: Año 6 | I30: Año 7 | J30: Año 8 | K30: Año 9 | L30: Año 10
A31: Cantidad de camarón (Lb) | C31: =C10 -> 918750 | D31: =D10 -> 1323000 | E31: =E10 -> 1543500 | F31: =F10 -> 1764000 | G31: =G10 -> 1984500 | H31: =H10 -> 1984500 | I31: =I10 -> 1984500 | J31: =J10 -> 1984500 | ... L31: =L10 -> 1984500
A32: Precio unitario de venta ($/Lb) | C32: =C12 -> 3 | D32: =D12 -> 3.21 | E32: =E12 -> 3.4347 | F32: =F12 -> 3.675129 | G32: =G12 -> 3.932388 | H32: =H12 -> 4.2076552 | I32: =I12 -> 4.5021911 | J32: =J12 -> 4.8173444 | ... L32: =L12 -> 5.5153776
A33: Ingresos | C33: =C32*C31 -> 2756250 | D33: =D32*D31 -> 4246830 | E33: =E32*E31 -> 5301459.5 | F33: =F32*F31 -> 6482927.6 | G33: =G32*G31 -> 7803824 | H33: =H32*H31 -> 8350091.7 | I33: =I32*I31 -> 8934598.1 | J33: =J32*J31 -> 9560020 | ... L33: =L32*L31 -> 10945267
A35: 2. Costos variables
A36: Calendario de costos variables
A37: Concepto | B37: Año 0 | C37: Año 1 | D37: Año 2 | E37: Año 3 | F37: Año 4 | G37: Año 5 | H37: Año 6 | I37: Año 7 | J37: Año 8 | K37: Año 9 | L37: Año 10
A38: Costos variables | C38: =C15 -> 1332187.5 | D38: =D15 -> 2052634.5 | E38: =E15 -> 2562372.1 | F38: =F15 -> 3133415 | G38: =G15 -> 3771848.3 | H38: =H15 -> 4035877.7 | I38: =I15 -> 4318389.1 | J38: =J15 -> 4620676.3 | ... L38: =L15 -> 5290212.3
A39: Total de costos variables | C39: =C38 -> 1332187.5 | D39: =D38 -> 2052634.5 | E39: =E38 -> 2562372.1 | F39: =F38 -> 3133415 | G39: =G38 -> 3771848.3 | H39: =H38 -> 4035877.7 | I39: =I38 -> 4318389.1 | J39: =J38 -> 4620676.3 | ... L39: =L38 -> 5290212.3
A41: 3. Costos fijos
A42: Calendario de los costos fijos
A43: Concepto | B43: Año 0 | C43: Año 1 | D43: Año 2 | E43: Año 3 | F43: Año 4 | G43: Año 5 | H43: Año 6 | I43: Año 7 | J43: Año 8 | K43: Año 9 | L43: Año 10
A44: Costos fijos de producción | C44: =C16 -> 50000 | D44: =D16 -> 53500 | E44: =E16 -> 57245 | F44: =F16 -> 61252.15 | G44: =G16 -> 65539.8 | H44: =H16 -> 70127.587 | I44: =I16 -> 75036.518 | J44: =J16 -> 80289.074 | ... L44: =L16 -> 91922.961
A45: Gastos administrativos | C45: =C17 -> 200000 | D45: =D17 -> 214000 | E45: =E17 -> 228980 | F45: =F17 -> 245008.6 | G45: =G17 -> 262159.2 | H45: =H17 -> 280510.35 | I45: =I17 -> 300146.07 | J45: =J17 -> 321156.3 | ... L45: =L17 -> 367691.84
A46: Total de costos fijos | C46: =SUM(C44:C45) -> 250000 | D46: =SUM(D44:D45) -> 267500 | E46: =SUM(E44:E45) -> 286225 | F46: =SUM(F44:F45) -> 306260.75 | G46: =SUM(G44:G45) -> 327699 | H46: =SUM(H44:H45) -> 350637.93 | I46: =SUM(I44:I45) -> 375182.59 | J46: =SUM(J44:J45) -> 401445.37 | ... L46: =SUM(L44:L45) -> 459614.8
A48: 4. Capital de trabajo
A49: Capital de trabajo
A50: Necesidad de Efectivo
A51: Concepto | B51: Año 0 | C51: Año 1 | D51: Año 2 | E51: Año 3 | F51: Año 4 | G51: Año 5 | H51: Año 6 | I51: Año 7 | J51: Año 8 | K51: Año 9 | L51: Año 10
A52: Capital de trabajo | C52: =C13+B52 -> 450000 | D52: =D13+C52 -> 700000 | E52: =E13+D52 -> 950000 | F52: =F13+E52 -> 1200000 | G52: =G13+F52 -> 1450000 | H52: =H13+G52 -> 1700000 | I52: =I13+H52 -> 1700000 | J52: =J13+I52 -> 1700000 | ... L52: =L13+K52 -> 1700000
A53: Efectivo requerido en caja | C53: =SUM(C52:C52) -> 450000 | D53: =SUM(D52:D52) -> 700000 | E53: =SUM(E52:E52) -> 950000 | F53: =SUM(F52:F52) -> 1200000 | G53: =SUM(G52:G52) -> 1450000 | H53: =SUM(H52:H52) -> 1700000 | I53: =SUM(I52:I52) -> 1700000 | J53: =SUM(J52:J52) -> 1700000 | ... L53: =SUM(L52:L52) -> 1700000
A55: Cálculo del Capital de Trabajo
A56: Concepto | B56: Cobertura | C56: Año 1 | D56: Año 2 | E56: Año 3 | F56: Año 4 | G56: Año 5 | H56: Año 6 | I56: Año 7 | J56: Año 8 | K56: Año 9 | L56: Año 10
A57: Activo circulante | C57: =C58 -> 450000 | D57: =D58 -> 700000 | E57: =E58 -> 950000 | F57: =F58 -> 1200000 | G57: =G58 -> 1450000 | H57: =H58 -> 1700000 | I57: =I58 -> 1700000 | J57: =J58 -> 1700000 | ... L57: =L58 -> 1700000
A58: Efectivo | C58: =C53 -> 450000 | D58: =D53 -> 700000 | E58: =E53 -> 950000 | F58: =F53 -> 1200000 | G58: =G53 -> 1450000 | H58: =H53 -> 1700000 | I58: =I53 -> 1700000 | J58: =J53 -> 1700000 | ... L58: =L53 -> 1700000
A59: Pasivo circulante | C59: =SUM(C60:C61) -> 0 | D59: =SUM(D60:D61) -> 0 | E59: =SUM(E60:E61) -> 0 | F59: =SUM(F60:F61) -> 0 | G59: =SUM(G60:G61) -> 0 | H59: =SUM(H60:H61) -> 0 | I59: =SUM(I60:I61) -> 0 | J59: =SUM(J60:J61) -> 0 | ... L59: =SUM(L60:L61) -> 0
A60: Cuentas por pagar | C60: 0 | D60: 0 | E60: 0 | F60: 0 | G60: 0 | H60: 0 | I60: 0 | J60: 0 | K60: 0 | L60: 0
A61: Proveedores | C61: 0 | D61: 0 | E61: 0 | F61: 0 | G61: 0 | H61: 0 | I61: 0 | J61: 0 | K61: 0 | L61: 0
A62: Capital de Trabajo (Ac - Pc) | C62: =C57-C59 -> 450000 | D62: =D57-D59 -> 700000 | E62: =E57-E59 -> 950000 | F62: =F57-F59 -> 1200000 | G62: =G57-G59 -> 1450000 | H62: =H57-H59 -> 1700000 | I62: =I57-I59 -> 1700000 | J62: =J57-J59 -> 1700000 | ... L62: =L57-L59 -> 1700000
A63: Incremento Capital Trabajo | B63: =C62-B62 -> 450000 | C63: =D62-C62 -> 250000 | D63: =E62-D62 -> 250000 | E63: =F62-E62 -> 250000 | F63: =G62-F62 -> 250000 | G63: =H62-G62 -> 250000 | H63: =I62-H62 -> 0 | I63: =J62-I62 -> 0 | ... L63: =M62-L62 -> -1700000
A65: 5. Inversiones
A66: Calendario de inversiones
A67: Concepto | B67: Año 0 | C67: Año 1 | D67: Año 2 | E67: Año 3 | F67: Año 4 | G67: Año 5 | H67: Año 6 | I67: Año 7 | J67: Año 8 | K67: Año 9 | L67: Año 10
A68: Activos Fijos
A69: Inversiones a 20 años | B69: 100000
A70: Inversiones a 10 años | B70: =3000000+200000+450000+50000 -> 3700000
A71: Inversiones a 5 años | B71: =300000+100000 -> 400000
A72: Inversion terrenos | B72: 750000
A73: Gastos Pre-operativos
A74: Gastos puesta en marcha | B74: 0
A75: Capital de trabajo
A76: Capital de trabajo | B76: =B63 -> 450000 | C76: =C63 -> 250000 | D76: =D63 -> 250000 | E76: =E63 -> 250000 | F76: =F63 -> 250000 | G76: =G63 -> 250000 | H76: =H63 -> 0 | I76: =I63 -> 0 | ... L76: =L63 -> -1700000
A77: Total Inversiones | B77: =SUM(B68:B76) -> 5400000 | C77: =SUM(C68:C76) -> 250000 | D77: =SUM(D68:D76) -> 250000 | E77: =SUM(E68:E76) -> 250000 | F77: =SUM(F68:F76) -> 250000 | G77: =SUM(G68:G76) -> 250000 | H77: =SUM(H68:H76) -> 0 | I77: =SUM(I68:I76) -> 0 | ... L77: =SUM(L68:L76) -> -1700000
A79: 6. Depreciaciones y Amortizaciones
A80: Calendario de Depreciaciones y Amortizaciones
A81: Concepto | B81: Año 0 | C81: Año 1 | D81: Año 2 | E81: Año 3 | F81: Año 4 | G81: Año 5 | H81: Año 6 | I81: Año 7 | J81: Año 8 | K81: Año 9 | L81: Año 10 | R81: Inversión | S81: Valor Activo | T81: Valor residual | U81: Vida útil | V81: Dep. Anual
A82: Inversiones a 20 años | C82: =$V$82 -> 2500 | D82: =$V$82 -> 2500 | E82: =$V$82 -> 2500 | F82: =$V$82 -> 2500 | G82: =$V$82 -> 2500 | H82: =$V$82 -> 2500 | I82: =$V$82 -> 2500 | J82: =$V$82 -> 2500 | ... L82: =$V$82 -> 2500 | R82: Edificio | S82: =B69 -> 100000 | T82: 50000 | U82: 20 | V82: =(S82-T82)/U82 -> 2500
A83: Inversiones a 10 años | C83: =$V$83+$V$84 -> 270000 | D83: =$V$83+$V$84 -> 270000 | E83: =$V$83+$V$84 -> 270000 | F83: =$V$83+$V$84 -> 270000 | G83: =$V$83+$V$84 -> 270000 | H83: =$V$83+$V$84 -> 270000 | I83: =$V$83+$V$84 -> 270000 | J83: =$V$83+$V$84 -> 270000 | ... L83: =$V$83+$V$84 -> 270000 | R83: Estanque y canales | S83: 3000000 | T83: 1000000 | U83: 10 | V83: =(S83-T83)/U83 -> 200000
A84: Inversiones a 5 años | C84: =$V$85 -> 80000 | D84: =$V$85 -> 80000 | E84: =$V$85 -> 80000 | F84: =$V$85 -> 80000 | G84: =$V$85 -> 80000 | H84: 0 | I84: 0 | J84: 0 | K84: 0 | L84: 0 | R84: Maq & Equipo | S84: =B70-S83 -> 700000 | T84: 0 | U84: 10 | V84: =(S84-T84)/U84 -> 70000
A85: Total Depreciación | C85: =SUM(C82:C84) -> 352500 | D85: =SUM(D82:D84) -> 352500 | E85: =SUM(E82:E84) -> 352500 | F85: =SUM(F82:F84) -> 352500 | G85: =SUM(G82:G84) -> 352500 | H85: =SUM(H82:H84) -> 272500 | I85: =SUM(I82:I84) -> 272500 | J85: =SUM(J82:J84) -> 272500 | ... L85: =SUM(L82:L84) -> 272500 | R85: Vehículos y embarcaciones | S85: =B71 -> 400000 | T85: 0 | U85: 5 | V85: =(S85-T85)/U85 -> 80000
S86: =SUM(S82:S85) -> 4200000
A87: Amortización pre-operativos | C87: =$B$74/10 -> 0 | D87: =$B$74/10 -> 0 | E87: =$B$74/10 -> 0 | F87: =$B$74/10 -> 0 | G87: =$B$74/10 -> 0 | H87: =$B$74/10 -> 0 | I87: =$B$74/10 -> 0 | J87: =$B$74/10 -> 0 | ... L87: =$B$74/10 -> 0
A88: Total Amortización | C88: =SUM(C87) -> 0 | D88: =SUM(D87) -> 0 | E88: =SUM(E87) -> 0 | F88: =SUM(F87) -> 0 | G88: =SUM(G87) -> 0 | H88: =SUM(H87) -> 0 | I88: =SUM(I87) -> 0 | J88: =SUM(J87) -> 0 | ... L88: =SUM(L87) -> 0
A90: 7. Valor de desecho del proyecto
A91: Clalculo del valor de desecho del proyecto (método contable)
A92: Concepto | B92: Valor del | C92: Depreciación por periodo | M92: Valor de
B93: Activo | C93: Año 1 | D93: Año 2 | E93: Año 3 | F93: Año 4 | G93: Año 5 | H93: Año 6 | I93: Año 7 | J93: Año 8 | K93: Año 9 | L93: Año 10 | M93: Desecho
A94: Inversiones a 20 años | B94: =B69 -> 100000 | C94: =C82 -> 2500 | D94: =D82 -> 2500 | E94: =E82 -> 2500 | F94: =F82 -> 2500 | G94: =G82 -> 2500 | H94: =H82 -> 2500 | I94: =I82 -> 2500 | J94: =J82 -> 2500 | ... L94: =L82 -> 2500 | M94: =B94-SUM(C94:L94) -> 75000
A95: Inversiones a 10 años | B95: =B70 -> 3700000 | C95: =C83 -> 270000 | D95: =D83 -> 270000 | E95: =E83 -> 270000 | F95: =F83 -> 270000 | G95: =G83 -> 270000 | H95: =H83 -> 270000 | I95: =I83 -> 270000 | J95: =J83 -> 270000 | ... L95: =L83 -> 270000 | M95: =B95-SUM(C95:L95) -> 1000000
A96: Inversiones a 5 años | B96: =B71 -> 400000 | C96: =C84 -> 80000 | D96: =D84 -> 80000 | E96: =E84 -> 80000 | F96: =F84 -> 80000 | G96: =G84 -> 80000 | H96: =H84 -> 0 | I96: =I84 -> 0 | J96: =J84 -> 0 | ... L96: =L84 -> 0 | M96: =B96-SUM(C96:L96) -> 0
A97: Amortización pre-operativos | B97: =B74 -> 0 | C97: =C87 -> 0 | D97: =D87 -> 0 | E97: =E87 -> 0 | F97: =F87 -> 0 | G97: =G87 -> 0 | H97: =H87 -> 0 | I97: =I87 -> 0 | J97: =J87 -> 0 | ... L97: =L87 -> 0 | M97: =B97-SUM(C97:L97) -> 0
A98: Valor de desecho total | M98: =SUM(M94:M97) -> 1075000
A100: 8. Financiamiento
A101: Cálculo del Financiamiento
A102: Financiamiento bancario (valor) | B102: =B77*E102 -> 2700000 | E102: 0.5
A103: Financiamiento bancario (tasa) | B103: =B22 -> 0.1
A104: Financiamiento bancario (periodos) | B104: 7 | C104: años
A105: Modalidad | B105: Pagos exactos
A107: Concepto | B107: Año 0 | C107: Año 1 | D107: Año 2 | E107: Año 3 | F107: Año 4 | G107: Año 5 | H107: Año 6 | I107: Año 7
A108: Saldo crédito | B108: =B102 -> 2700000 | C108: =B108-C111 -> 2700000 | D108: =C108-D111 -> 2700000 | E108: =D108-E111 -> 2700000 | F108: =E108-F111 -> 2700000 | G108: =F108-G111 -> 2700000 | H108: =G108-H111 -> 2700000 | I108: =H108-I111 -> 0
A109: Cuota mensual (anualidad) | C109: =C110 -> 270000 | D109: =D110 -> 270000 | E109: =E110 -> 270000 | F109: =F110 -> 270000 | G109: =G110 -> 270000 | H109: =H110 -> 270000 | I109: =H108+(H108*B103) -> 2970000
A110: Intereses | C110: =B108*$B$103 -> 270000 | D110: =C108*$B$103 -> 270000 | E110: =D108*$B$103 -> 270000 | F110: =E108*$B$103 -> 270000 | G110: =F108*$B$103 -> 270000 | H110: =G108*$B$103 -> 270000 | I110: =H108*$B$103 -> 270000
A111: Abono a capital (amortización) | C111: =C109-C110 -> 0 | D111: =D109-D110 -> 0 | E111: =E109-E110 -> 0 | F111: =F109-F110 -> 0 | G111: =G109-G110 -> 0 | H111: =H109-H110 -> 0 | I111: =I109-I110 -> 2700000
A113: 9.Flujo de caja del proyecto
...

Sheet Italiano
A1: Camaronera Industrial
A3: Variables
A4: Horizonte de evaluación (años) | B4: 10
A5: Devaluación | B5: 0.05
A6: Inflación | B6: 0.07
B7: Año 0 | C7: Año 1 | D7: Año 2 | E7: Año 3 | F7: Año 4 | G7: Año 5 | H7: Año 6 | I7: Año 7 | J7: Año 8 | K7: Año 9 | L7: Año 10
A8: Área en producción (Ha) | C8: 750 | D8: 900 | E8: 900 | F8: 900 | G8: 900 | H8: 900 | I8: 900 | J8: 900 | K8: 900 | L8: 900
A9: Producción neta (Lb/Ha/año) | C9: =1225 -> 1225 | D9: =1470 -> 1470 | E9: =1715 -> 1715 | F9: =1960 -> 1960 | G9: =2205 -> 2205 | H9: =2205 -> 2205 | I9: =2205 -> 2205 | J9: =2205 -> 2205 | K9: =2205 -> 2205 | L9: =2205 -> 2205
A10: Producción neta total (Lb/año) | C10: =C9*C8 -> 918750 | D10: =D9*D8 -> 1323000 | E10: =E9*E8 -> 1543500 | F10: =F9*F8 -> 1764000 | G10: =G9*G8 -> 1984500 | H10: =H9*H8 -> 1984500 | I10: =I9*I8 -> 1984500 | J10: =J9*J8 -> 1984500 | ... L10: =L9*L8 -> 1984500
A11: Tasa de cambio | C11: 1 | D11: =C11+(C11*$B$5) -> 1.05 | E11: =D11+(D11*$B$5) -> 1.1025 | F11: =E11+(E11*$B$5) -> 1.157625 | G11: =F11+(F11*$B$5) -> 1.2155063 | H11: =G11+(G11*$B$5) -> 1.2762816 | I11: =H11+(H11*$B$5) -> 1.3400956 | J11: =I11+(I11*$B$5) -> 1.4071004 | K11: =J11+(J11*$B$5) -> 1.4774554 | L11: =K11+(K11*$B$5) -> 1.5513282
A12: Precio de venta FOB ($/Lb) | C12: 3 | D12: =C12+(C12*$B$6) -> 3.21 | E12: =D12+(D12*$B$6) -> 3.4347 | F12: =E12+(E12*$B$6) -> 3.675129 | G12: =F12+(F12*$B$6) -> 3.932388 | H12: =G12+(G12*$B$6) -> 4.2076552 | I12: =H12+(H12*$B$6) -> 4.5021911 | J12: =I12+(I12*$B$6) -> 4.8173444 | K12: =J12+(J12*$B$6) -> 5.1545585 | L12: =K12+(K12*$B$6) -> 5.5153776
A13: Capital de trabajo | C13: 450000 | D13: 250000 | E13: 250000 | F13: 250000 | G13: 250000 | H13: 250000 | I13: 0 | J13: 0 | K13: 0 | L13: 0
A14: Costos variables ($1.45 x Lb) | C14: =1.45 -> 1.45 | D14: =C14+(C14*$B$6) -> 1.5515 | E14: =D14+(D14*$B$6) -> 1.660105 | F14: =E14+(E14*$B$6) -> 1.7763123 | G14: =F14+(F14*$B$6) -> 1.9006542 | H14: =G14+(G14*$B$6) -> 2.0337 | I14: =H14+(H14*$B$6) -> 2.176059 | J14: =I14+(I14*$B$6) -> 2.3283831 | K14: =J14+(J14*$B$6) -> 2.49137 | L14: =K14+(K14*$B$6) -> 2.6657659
A15: Costos variables anuales | C15: =C14*C10 -> 1332187.5 | D15: =D14*D10 -> 2052634.5 | E15: =E14*E10 -> 2562372.1 | F15: =F14*F10 -> 3133415 | G15: =G14*G10 -> 3771848.3 | H15: =H14*H10 -> 4035877.7 | I15: =I14*I10 -> 4318389.1 | J15: =J14*J10 -> 4620676.3 | ... L15: =L14*L10 -> 5290212.3
A16: Costos fijos de producción | C16: 50000 | D16: =C16+(C16*$B$6) -> 53500 | E16: =D16+(D16*$B$6) -> 57245 | F16: =E16+(E16*$B$6) -> 61252.15 | G16: =F16+(F16*$B$6) -> 65539.8 | H16: =G16+(G16*$B$6) -> 70127.587 | I16: =H16+(H16*$B$6) -> 75036.518 | J16: =I16+(I16*$B$6) -> 80289.074 | K16: =J16+(J16*$B$6) -> 85909.309 | L16: =K16+(K16*$B$6) -> 91922.961
A17: Gastos administrativos | C17: 200000 | D17: =C17+(C17*$B$6) -> 214000 | E17: =D17+(D17*$B$6) -> 228980 | F17: =E17+(E17*$B$6) -> 245008.6 | G17: =F17+(F17*$B$6) -> 262159.2 | H17: =G17+(G17*$B$6) -> 280510.35 | I17: =H17+(H17*$B$6) -> 300146.07 | J17: =I17+(I17*$B$6) -> 321156.3 | K17: =J17+(J17*$B$6) -> 343637.24 | L17: =K17+(K17*$B$6) -> 367691.84
A19: Valor residual del terreno | B19: 1250000
A20: Valor residual de estanques y canales | B20: 1000000
A21: Valor residual de edificios | B21: 50000
A22: Tasa de fiananciamiento bancario | B22: 0.1
A23: Plazo del financiamiento bancario (años) | B23: 7
A24: Plazo del financiamiento bancario (valor) | B24: =5400000*0.5 -> 2700000
A25: Tasa de corte | B25: 0.19
A26: Tasa de ISR | B26: 0.3
A28: 1. Ingresos del proyecto
A29: Calendario de ingresos (venta del producto)
A30: Concepto | B30: Año 0 | C30: Año 1 | D30: Año 2 | E30: Año 3 | F30: Año 4 | G30: Año 5 | H30: Año 6 | I30: Año 7 | J30: Año 8 | K30: Año 9 | L30: Año 10
A31: Cantidad de camarón (Lb) | C31: =C10 -> 918750 | D31: =D10 -> 1323000 | E31: =E10 -> 1543500 | F31: =F10 -> 1764000 | G31: =G10 -> 1984500 | H31: =H10 -> 1984500 | I31: =I10 -> 1984500 | J31: =J10 -> 1984500 | ... L31: =L10 -> 1984500
A32: Precio unitario de venta ($/Lb) | C32: =C12 -> 3 | D32: =D12 -> 3.21 | E32: =E12 -> 3.4347 | F32: =F12 -> 3.675129 | G32: =G12 -> 3.932388 | H32: =H12 -> 4.2076552 | I32: =I12 -> 4.5021911 | J32: =J12 -> 4.8173444 | ... L32: =L12 -> 5.5153776
A33: Ingresos | C33: =C32*C31 -> 2756250 | D33: =D32*D31 -> 4246830 | E33: =E32*E31 -> 5301459.5 | F33: =F32*F31 -> 6482927.6 | G33: =G32*G31 -> 7803824 | H33: =H32*H31 -> 8350091.7 | I33: =I32*I31 -> 8934598.1 | J33: =J32*J31 -> 9560020 | ... L33: =L32*L31 -> 10945267
A35: 2. Costos variables
A36: Calendario de costos variables
A37: Concepto | B37: Año 0 | C37: Año 1 | D37: Año 2 | E37: Año 3 | F37: Año 4 | G37: Año 5 | H37: Año 6 | I37: Año 7 | J37: Año 8 | K37: Año 9 | L37: Año 10
A38: Costos variables | C38: =C15 -> 1332187.5 | D38: =D15 -> 2052634.5 | E38: =E15 -> 2562372.1 | F38: =F15 -> 3133415 | G38: =G15 -> 3771848.3 | H38: =H15 -> 4035877.7 | I38: =I15 -> 4318389.1 | J38: =J15 -> 4620676.3 | ... L38: =L15 -> 5290212.3
A39: Total de costos variables | C39: =C38 -> 1332187.5 | D39: =D38 -> 2052634.5 | E39: =E38 -> 2562372.1 | F39: =F38 -> 3133415 | G39: =G38 -> 3771848.3 | H39: =H38 -> 4035877.7 | I39: =I38 -> 4318389.1 | J39: =J38 -> 4620676.3 | ... L39: =L38 -> 5290212.3
A41: 3. Costos fijos
A42: Calendario de los costos fijos
A43: Concepto | B43: Año 0 | C43: Año 1 | D43: Año 2 | E43: Año 3 | F43: Año 4 | G43: Año 5 | H43: Año 6 | I43: Año 7 | J43: Año 8 | K43: Año 9 | L43: Año 10
A44: Costos fijos de producción | C44: =C16 -> 50000 | D44: =D16 -> 53500 | E44: =E16 -> 57245 | F44: =F16 -> 61252.15 | G44: =G16 -> 65539.8 | H44: =H16 -> 70127.587 | I44: =I16 -> 75036.518 | J44: =J16 -> 80289.074 | ... L44: =L16 -> 91922.961
A45: Gastos administrativos | C45: =C17 -> 200000 | D45: =D17 -> 214000 | E45: =E17 -> 228980 | F45: =F17 -> 245008.6 | G45: =G17 -> 262159.2 | H45: =H17 -> 280510.35 | I45: =I17 -> 300146.07 | J45: =J17 -> 321156.3 | ... L45: =L17 -> 367691.84
A46: Total de costos fijos | C46: =SUM(C44:C45) -> 250000 | D46: =SUM(D44:D45) -> 267500 | E46: =SUM(E44:E45) -> 286225 | F46: =SUM(F44:F45) -> 306260.75 | G46: =SUM(G44:G45) -> 327699 | H46: =SUM(H44:H45) -> 350637.93 | I46: =SUM(I44:I45) -> 375182.59 | J46: =SUM(J44:J45) -> 401445.37 | ... L46: =SUM(L44:L45) -> 459614.8
A48: 4. Capital de trabajo
A49: Capital de trabajo
A50: Necesidad de Efectivo
A51: Concepto | B51: Año 0 | C51: Año 1 | D51: Año 2 | E51: Año 3 | F51: Año 4 | G51: Año 5 | H51: Año 6 | I51: Año 7 | J51: Año 8 | K51: Año 9 | L51: Año 10
A52: Capital de trabajo | C52: =C13+B52 -> 450000 | D52: =D13+C52 -> 700000 | E52: =E13+D52 -> 950000 | F52: =F13+E52 -> 1200000 | G52: =G13+F52 -> 1450000 | H52: =H13+G52 -> 1700000 | I52: =I13+H52 -> 1700000 | J52: =J13+I52 -> 1700000 | ... L52: =L13+K52 -> 1700000
A53: Efectivo requerido en caja | C53: =SUM(C52:C52) -> 450000 | D53: =SUM(D52:D52) -> 700000 | E53: =SUM(E52:E52) -> 950000 | F53: =SUM(F52:F52) -> 1200000 | G53: =SUM(G52:G52) -> 1450000 | H53: =SUM(H52:H52) -> 1700000 | I53: =SUM(I52:I52) -> 1700000 | J53: =SUM(J52:J52) -> 1700000 | ... L53: =SUM(L52:L52) -> 1700000
A55: Cálculo del Capital de Trabajo
A56: Concepto | B56: Cobertura | C56: Año 1 | D56: Año 2 | E56: Año 3 | F56: Año 4 | G56: Año 5 | H56: Año 6 | I56: Año 7 | J56: Año 8 | K56: Año 9 | L56: Año 10
A57: Activo circulante | C57: =C58 -> 450000 | D57: =D58 -> 700000 | E57: =E58 -> 950000 | F57: =F58 -> 1200000 | G57: =G58 -> 1450000 | H57: =H58 -> 1700000 | I57: =I58 -> 1700000 | J57: =J58 -> 1700000 | ... L57: =L58 -> 1700000
A58: Efectivo | C58: =C53 -> 450000 | D58: =D53 -> 700000 | E58: =E53 -> 950000 | F58: =F53 -> 1200000 | G58: =G53 -> 1450000 | H58: =H53 -> 1700000 | I58: =I53 -> 1700000 | J58: =J53 -> 1700000 | ... L58: =L53 -> 1700000
A59: Pasivo circulante | C59: =SUM(C60:C61) -> 0 | D59: =SUM(D60:D61) -> 0 | E59: =SUM(E60:E61) -> 0 | F59: =SUM(F60:F61) -> 0 | G59: =SUM(G60:G61) -> 0 | H59: =SUM(H60:H61) -> 0 | I59: =SUM(I60:I61) -> 0 | J59: =SUM(J60:J61) -> 0 | ... L59: =SUM(L60:L61) -> 0
A60: Cuentas por pagar | C60: 0 | D60: 0 | E60: 0 | F60: 0 | G60: 0 | H60: 0 | I60: 0 | J60: 0 | K60: 0 | L60: 0
A61: Proveedores | C61: 0 | D61: 0 | E61: 0 | F61: 0 | G61: 0 | H61: 0 | I61: 0 | J61: 0 | K61: 0 | L61: 0
A62: Capital de Trabajo (Ac - Pc) | C62: =C57-C59 -> 450000 | D62: =D57-D59 -> 700000 | E62: =E57-E59 -> 950000 | F62: =F57-F59 -> 1200000 | G62: =G57-G59 -> 1450000 | H62: =H57-H59 -> 1700000 | I62: =I57-I59 -> 1700000 | J62: =J57-J59 -> 1700000 | ... L62: =L57-L59 -> 1700000
A63: Incremento Capital Trabajo | B63: =C62-B62 -> 450000 | C63: =D62-C62 -> 250000 | D63: =E62-D62 -> 250000 | E63: =F62-E62 -> 250000 | F63: =G62-F62 -> 250000 | G63: =H62-G62 -> 250000 | H63: =I62-H62 -> 0 | I63: =J62-I62 -> 0 | ... L63: =M62-L62 -> -1700000
A65: 5. Inversiones
A66: Calendario de inversiones
A67: Concepto | B67: Año 0 | C67: Año 1 | D67: Año 2 | E67: Año 3 | F67: Año 4 | G67: Año 5 | H67: Año 6 | I67: Año 7 | J67: Año 8 | K67: Año 9 | L67: Año 10
A68: Activos Fijos
A69: Inversiones a 20 años | B69: 100000
A70: Inversiones a 10 años | B70: =3000000+200000+450000+50000 -> 3700000
A71: Inversiones a 5 años | B71: =300000+100000 -> 400000
A72: Inversion terrenos | B72: 750000
A73: Gastos Pre-operativos
A74: Gastos puesta en marcha | B74: 0
A75: Capital de trabajo
A76: Capital de trabajo | B76: =B63 -> 450000 | C76: =C63 -> 250000 | D76: =D63 -> 250000 | E76: =E63 -> 250000 | F76: =F63 -> 250000 | G76: =G63 -> 250000 | H76: =H63 -> 0 | I76: =I63 -> 0 | ... L76: =L63 -> -1700000
A77: Total Inversiones | B77: =SUM(B68:B76) -> 5400000 | C77: =SUM(C68:C76) -> 250000 | D77: =SUM(D68:D76) -> 250000 | E77: =SUM(E68:E76) -> 250000 | F77: =SUM(F68:F76) -> 250000 | G77: =SUM(G68:G76) -> 250000 | H77: =SUM(H68:H76) -> 0 | I77: =SUM(I68:I76) -> 0 | ... L77: =SUM(L68:L76) -> -1700000
A79: 6. Depreciaciones y Amortizaciones
A80: Calendario de Depreciaciones y Amortizaciones
A81: Concepto | B81: Año 0 | C81: Año 1 | D81: Año 2 | E81: Año 3 | F81: Año 4 | G81: Año 5 | H81: Año 6 | I81: Año 7 | J81: Año 8 | K81: Año 9 | L81: Año 10 | R81: Inversión | S81: Valor Activo | T81: Valor residual | U81: Vida útil | V81: Dep. Anual
A82: Inversiones a 20 años | C82: =$V$82 -> 2500 | D82: =$V$82 -> 2500 | E82: =$V$82 -> 2500 | F82: =$V$82 -> 2500 | G82: =$V$82 -> 2500 | H82: =$V$82 -> 2500 | I82: =$V$82 -> 2500 | J82: =$V$82 -> 2500 | ... L82: =$V$82 -> 2500 | R82: Edificio | S82: =B69 -> 100000 | T82: 50000 | U82: 20 | V82: =(S82-T82)/U82 -> 2500
A83: Inversiones a 10 años | C83: =$V$83+$V$84 -> 270000 | D83: =$V$83+$V$84 -> 270000 | E83: =$V$83+$V$84 -> 270000 | F83: =$V$83+$V$84 -> 270000 | G83: =$V$83+$V$84 -> 270000 | H83: =$V$83+$V$84 -> 270000 | I83: =$V$83+$V$84 -> 270000 | J83: =$V$83+$V$84 -> 270000 | ... L83: =$V$83+$V$84 -> 270000 | R83: Estanque y canales | S83: 3000000 | T83: 1000000 | U83: 10 | V83: =(S83-T83)/U83 -> 200000
A84: Inversiones a 5 años | C84: =$V$85 -> 80000 | D84: =$V$85 -> 80000 | E84: =$V$85 -> 80000 | F84: =$V$85 -> 80000 | G84: =$V$85 -> 80000 | H84: 0 | I84: 0 | J84: 0 | K84: 0 | L84: 0 | R84: Maq & Equipo | S84: =B70-S83 -> 700000 | T84: 0 | U84: 10 | V84: =(S84-T84)/U84 -> 70000
A85: Total Depreciación | C85: =SUM(C82:C84) -> 352500 | D85: =SUM(D82:D84) -> 352500 | E85: =SUM(E82:E84) -> 352500 | F85: =SUM(F82:F84) -> 352500 | G85: =SUM(G82:G84) -> 352500 | H85: =SUM(H82:H84) -> 272500 | I85: =SUM(I82:I84) -> 272500 | J85: =SUM(J82:J84) -> 272500 | ... L85: =SUM(L82:L84) -> 272500 | R85: Vehículos y embarcaciones | S85: =B71 -> 400000 | T85: 0 | U85: 5 | V85: =(S85-T85)/U85 -> 80000
S86: =SUM(S82:S85) -> 4200000
A87: Amortización pre-operativos | C87: =$B$74/10 -> 0 | D87: =$B$74/10 -> 0 | E87: =$B$74/10 -> 0 | F87: =$B$74/10 -> 0 | G87: =$B$74/10 -> 0 | H87: =$B$74/10 -> 0 | I87: =$B$74/10 -> 0 | J87: =$B$74/10 -> 0 | ... L87: =$B$74/10 -> 0
A88: Total Amortización | C88: =SUM(C87) -> 0 | D88: =SUM(D87) -> 0 | E88: =SUM(E87) -> 0 | F88: =SUM(F87) -> 0 | G88: =SUM(G87) -> 0 | H88: =SUM(H87) -> 0 | I88: =SUM(I87) -> 0 | J88: =SUM(J87) -> 0 | ... L88: =SUM(L87) -> 0
A90: 7. Valor de desecho del proyecto
A91: Clalculo del valor de desecho del proyecto (método contable)
A92: Concepto | B92: Valor del | C92: Depreciación por periodo | M92: Valor de
B93: Activo | C93: Año 1 | D93: Año 2 | E93: Año 3 | F93: Año 4 | G93: Año 5 | H93: Año 6 | I93: Año 7 | J93: Año 8 | K93: Año 9 | L93: Año 10 | M93: Desecho
A94: Inversiones a 20 años | B94: =B69 -> 100000 | C94: =C82 -> 2500 | D94: =D82 -> 2500 | E94: =E82 -> 2500 | F94: =F82 -> 2500 | G94: =G82 -> 2500 | H94: =H82 -> 2500 | I94: =I82 -> 2500 | J94: =J82 -> 2500 | ... L94: =L82 -> 2500 | M94: =B94-SUM(C94:L94) -> 75000
A95: Inversiones a 10 años | B95: =B70 -> 3700000 | C95: =C83 -> 270000 | D95: =D83 -> 270000 | E95: =E83 -> 270000 | F95: =F83 -> 270000 | G95: =G83 -> 270000 | H95: =H83 -> 270000 | I95: =I83 -> 270000 | J95: =J83 -> 270000 | ... L95: =L83 -> 270000 | M95: =B95-SUM(C95:L95) -> 1000000
A96: Inversiones a 5 años | B96: =B71 -> 400000 | C96: =C84 -> 80000 | D96: =D84 -> 80000 | E96: =E84 -> 80000 | F96: =F84 -> 80000 | G96: =G84 -> 80000 | H96: =H84 -> 0 | I96: =I84 -> 0 | J96: =J84 -> 0 | ... L96: =L84 -> 0 | M96: =B96-SUM(C96:L96) -> 0
A97: Amortización pre-operativos | B97: =B74 -> 0 | C97: =C87 -> 0 | D97: =D87 -> 0 | E97: =E87 -> 0 | F97: =F87 -> 0 | G97: =G87 -> 0 | H97: =H87 -> 0 | I97: =I87 -> 0 | J97: =J87 -> 0 | ... L97: =L87 -> 0 | M97: =B97-SUM(C97:L97) -> 0
A98: Valor de desecho total | M98: =SUM(M94:M97) -> 1075000
A100: 8. Financiamiento
A101: Cálculo del Financiamiento
A102: Financiamiento bancario (valor) | B102: =B77*E102 -> 2700000 | E102: 0.5
A103: Financiamiento bancario (tasa) | B103: =B22 -> 0.1
A104: Financiamiento bancario (periodos) | B104: 7 | C104: años
A105: Modalidad | B105: Pagos exactos
A107: Concepto | B107: Año 0 | C107: Año 1 | D107: Año 2 | E107: Año 3 | F107: Año 4 | G107: Año 5 | H107: Año 6 | I107: Año 7
A108: Saldo crédito | B108: =B102 -> 2700000 | C108: =B108-C111 -> 2314285.7 | D108: =C108-D111 -> 1928571.4 | E108: =D108-E111 -> 1542857.1 | F108: =E108-F111 -> 1157142.9 | G108: =F108-G111 -> 771428.57 | H108: =G108-H111 -> 385714.29 | I108: =H108-I111 -> 0
A109: Cuota mensual (anualidad) | C109: =C110+C111 -> 655714.29 | D109: =D110+D111 -> 617142.86 | E109: =E110+E111 -> 578571.43 | F109: =F110+F111 -> 540000 | G109: =G110+G111 -> 501428.57 | H109: =H110+H111 -> 462857.14 | I109: =I110+I111 -> 424285.71
A110: Intereses | C110: =B108*$B$103 -> 270000 | D110: =C108*$B$103 -> 231428.57 | E110: =D108*$B$103 -> 192857.14 | F110: =E108*$B$103 -> 154285.71 | G110: =F108*$B$103 -> 115714.29 | H110: =G108*$B$103 -> 77142.857 | I110: =H108*$B$103 -> 38571.429
A111: Abono a capital (amortización) | C111: =$B$102/$B$104 -> 385714.29 | D111: =$B$102/$B$104 -> 385714.29 | E111: =$B$102/$B$104 -> 385714.29 | F111: =$B$102/$B$104 -> 385714.29 | G111: =$B$102/$B$104 -> 385714.29 | H111: =$B$102/$B$104 -> 385714.29 | I111: =$B$102/$B$104 -> 385714.29
A113: 9.Flujo de caja del proyecto
...

Sheet Alemán
A1: Camaronera Industrial
A3: Variables
A4: Horizonte de evaluación (años) | B4: 10
A5: Devaluación | B5: 0.05
A6: Inflación | B6: 0.07
B7: Año 0 | C7: Año 1 | D7: Año 2 | E7: Año 3 | F7: Año 4 | G7: Año 5 | H7: Año 6 | I7: Año 7 | J7: Año 8 | K7: Año 9 | L7: Año 10
A8: Área en producción (Ha) | C8: 750 | D8: 900 | E8: 900 | F8: 900 | G8: 900 | H8: 900 | I8: 900 | J8: 900 | K8: 900 | L8: 900
A9: Producción neta (Lb/Ha/año) | C9: =1225 -> 1225 | D9: =1470 -> 1470 | E9: =1715 -> 1715 | F9: =1960 -> 1960 | G9: =2205 -> 2205 | H9: =2205 -> 2205 | I9: =2205 -> 2205 | J9: =2205 -> 2205 | K9: =2205 -> 2205 | L9: =2205 -> 2205
A10: Producción neta total (Lb/año) | C10: =C9*C8 -> 918750 | D10: =D9*D8 -> 1323000 | E10: =E9*E8 -> 1543500 | F10: =F9*F8 -> 1764000 | G10: =G9*G8 -> 1984500 | H10: =H9*H8 -> 1984500 | I10: =I9*I8 -> 1984500 | J10: =J9*J8 -> 1984500 | ... L10: =L9*L8 -> 1984500
A11: Tasa de cambio | C11: 1 | D11: =C11+(C11*$B$5) -> 1.05 | E11: =D11+(D11*$B$5) -> 1.1025 | F11: =E11+(E11*$B$5) -> 1.157625 | G11: =F11+(F11*$B$5) -> 1.2155063 | H11: =G11+(G11*$B$5) -> 1.2762816 | I11: =H11+(H11*$B$5) -> 1.3400956 | J11: =I11+(I11*$B$5) -> 1.4071004 | K11: =J11+(J11*$B$5) -> 1.4774554 | L11: =K11+(K11*$B$5) -> 1.5513282
A12: Precio de venta FOB ($/Lb) | C12: 3 | D12: =C12+(C12*$B$6) -> 3.21 | E12: =D12+(D12*$B$6) -> 3.4347 | F12: =E12+(E12*$B$6) -> 3.675129 | G12: =F12+(F12*$B$6) -> 3.932388 | H12: =G12+(G12*$B$6) -> 4.2076552 | I12: =H12+(H12*$B$6) -> 4.5021911 | J12: =I12+(I12*$B$6) -> 4.8173444 | K12: =J12+(J12*$B$6) -> 5.1545585 | L12: =K12+(K12*$B$6) -> 5.5153776
A13: Capital de trabajo | C13: 450000 | D13: 250000 | E13: 250000 | F13: 250000 | G13: 250000 | H13: 250000 | I13: 0 | J13: 0 | K13: 0 | L13: 0
A14: Costos variables ($1.45 x Lb) | C14: =1.45 -> 1.45 | D14: =C14+(C14*$B$6) -> 1.5515 | E14: =D14+(D14*$B$6) -> 1.660105 | F14: =E14+(E14*$B$6) -> 1.7763123 | G14: =F14+(F14*$B$6) -> 1.9006542 | H14: =G14+(G14*$B$6) -> 2.0337 | I14: =H14+(H14*$B$6) -> 2.176059 | J14: =I14+(I14*$B$6) -> 2.3283831 | K14: =J14+(J14*$B$6) -> 2.49137 | L14: =K14+(K14*$B$6) -> 2.6657659
A15: Costos variables anuales | C15: =C14*C10 -> 1332187.5 | D15: =D14*D10 -> 2052634.5 | E15: =E14*E10 -> 2562372.1 | F15: =F14*F10 -> 3133415 | G15: =G14*G10 -> 3771848.3 | H15: =H14*H10 -> 4035877.7 | I15: =I14*I10 -> 4318389.1 | J15: =J14*J10 -> 4620676.3 | ... L15: =L14*L10 -> 5290212.3
A16: Costos fijos de producción | C16: 50000 | D16: =C16+(C16*$B$6) -> 53500 | E16: =D16+(D16*$B$6) -> 57245 | F16: =E16+(E16*$B$6) -> 61252.15 | G16: =F16+(F16*$B$6) -> 65539.8 | H16: =G16+(G16*$B$6) -> 70127.587 | I16: =H16+(H16*$B$6) -> 75036.518 | J16: =I16+(I16*$B$6) -> 80289.074 | K16: =J16+(J16*$B$6) -> 85909.309 | L16: =K16+(K16*$B$6) -> 91922.961
A17: Gastos administrativos | C17: 200000 | D17: =C17+(C17*$B$6) -> 214000 | E17: =D17+(D17*$B$6) -> 228980 | F17: =E17+(E17*$B$6) -> 245008.6 | G17: =F17+(F17*$B$6) -> 262159.2 | H17: =G17+(G17*$B$6) -> 280510.35 | I17: =H17+(H17*$B$6) -> 300146.07 | J17: =I17+(I17*$B$6) -> 321156.3 | K17: =J17+(J17*$B$6) -> 343637.24 | L17: =K17+(K17*$B$6) -> 367691.84
A19: Valor residual del terreno | B19: 1250000
A20: Valor residual de estanques y canales | B20: 1000000
A21: Valor residual de edificios | B21: 50000
A22: Tasa de fiananciamiento bancario | B22: 0.1
A23: Plazo del financiamiento bancario (años) | B23: 7
A24: Plazo del financiamiento bancario (valor) | B24: =5400000*0.5 -> 2700000
A25: Tasa de corte | B25: 0.19
A26: Tasa de ISR | B26: 0.3
A28: 1. Ingresos del proyecto
A29: Calendario de ingresos (venta del producto)
A30: Concepto | B30: Año 0 | C30: Año 1 | D30: Año 2 | E30: Año 3 | F30: Año 4 | G30: Año 5 | H30: Año 6 | I30: Año 7 | J30: Año 8 | K30: Año 9 | L30: Año 10
A31: Cantidad de camarón (Lb) | C31: =C10 -> 918750 | D31: =D10 -> 1323000 | E31: =E10 -> 1543500 | F31: =F10 -> 1764000 | G31: =G10 -> 1984500 | H31: =H10 -> 1984500 | I31: =I10 -> 1984500 | J31: =J10 -> 1984500 | ... L31: =L10 -> 1984500
A32: Precio unitario de venta ($/Lb) | C32: =C12 -> 3 | D32: =D12 -> 3.21 | E32: =E12 -> 3.4347 | F32: =F12 -> 3.675129 | G32: =G12 -> 3.932388 | H32: =H12 -> 4.2076552 | I32: =I12 -> 4.5021911 | J32: =J12 -> 4.8173444 | ... L32: =L12 -> 5.5153776
A33: Ingresos | C33: =C32*C31 -> 2756250 | D33: =D32*D31 -> 4246830 | E33: =E32*E31 -> 5301459.5 | F33: =F32*F31 -> 6482927.6 | G33: =G32*G31 -> 7803824 | H33: =H32*H31 -> 8350091.7 | I33: =I32*I31 -> 8934598.1 | J33: =J32*J31 -> 9560020 | ... L33: =L32*L31 -> 10945267
A35: 2. Costos variables
A36: Calendario de costos variables
A37: Concepto | B37: Año 0 | C37: Año 1 | D37: Año 2 | E37: Año 3 | F37: Año 4 | G37: Año 5 | H37: Año 6 | I37: Año 7 | J37: Año 8 | K37: Año 9 | L37: Año 10
A38: Costos variables | C38: =C15 -> 1332187.5 | D38: =D15 -> 2052634.5 | E38: =E15 -> 2562372.1 | F38: =F15 -> 3133415 | G38: =G15 -> 3771848.3 | H38: =H15 -> 4035877.7 | I38: =I15 -> 4318389.1 | J38: =J15 -> 4620676.3 | ... L38: =L15 -> 5290212.3
A39: Total de costos variables | C39: =C38 -> 1332187.5 | D39: =D38 -> 2052634.5 | E39: =E38 -> 2562372.1 | F39: =F38 -> 3133415 | G39: =G38 -> 3771848.3 | H39: =H38 -> 4035877.7 | I39: =I38 -> 4318389.1 | J39: =J38 -> 4620676.3 | ... L39: =L38 -> 5290212.3
A41: 3. Costos fijos
A42: Calendario de los costos fijos
A43: Concepto | B43: Año 0 | C43: Año 1 | D43: Año 2 | E43: Año 3 | F43: Año 4 | G43: Año 5 | H43: Año 6 | I43: Año 7 | J43: Año 8 | K43: Año 9 | L43: Año 10
A44: Costos fijos de producción | C44: =C16 -> 50000 | D44: =D16 -> 53500 | E44: =E16 -> 57245 | F44: =F16 -> 61252.15 | G44: =G16 -> 65539.8 | H44: =H16 -> 70127.587 | I44: =I16 -> 75036.518 | J44: =J16 -> 80289.074 | ... L44: =L16 -> 91922.961
A45: Gastos administrativos | C45: =C17 -> 200000 | D45: =D17 -> 214000 | E45: =E17 -> 228980 | F45: =F17 -> 245008.6 | G45: =G17 -> 262159.2 | H45: =H17 -> 280510.35 | I45: =I17 -> 300146.07 | J45: =J17 -> 321156.3 | ... L45: =L17 -> 367691.84
A46: Total de costos fijos | C46: =SUM(C44:C45) -> 250000 | D46: =SUM(D44:D45) -> 267500 | E46: =SUM(E44:E45) -> 286225 | F46: =SUM(F44:F45) -> 306260.75 | G46: =SUM(G44:G45) -> 327699 | H46: =SUM(H44:H45) -> 350637.93 | I46: =SUM(I44:I45) -> 375182.59 | J46: =SUM(J44:J45) -> 401445.37 | ... L46: =SUM(L44:L45) -> 459614.8
A48: 4. Capital de trabajo
A49: Capital de trabajo
A50: Necesidad de Efectivo
A51: Concepto | B51: Año 0 | C51: Año 1 | D51: Año 2 | E51: Año 3 | F51: Año 4 | G51: Año 5 | H51: Año 6 | I51: Año 7 | J51: Año 8 | K51: Año 9 | L51: Año 10
A52: Capital de trabajo | C52: =C13+B52 -> 450000 | D52: =D13+C52 -> 700000 | E52: =E13+D52 -> 950000 | F52: =F13+E52 -> 1200000 | G52: =G13+F52 -> 1450000 | H52: =H13+G52 -> 1700000 | I52: =I13+H52 -> 1700000 | J52: =J13+I52 -> 1700000 | ... L52: =L13+K52 -> 1700000
A53: Efectivo requerido en caja | C53: =SUM(C52:C52) -> 450000 | D53: =SUM(D52:D52) -> 700000 | E53: =SUM(E52:E52) -> 950000 | F53: =SUM(F52:F52) -> 1200000 | G53: =SUM(G52:G52) -> 1450000 | H53: =SUM(H52:H52) -> 1700000 | I53: =SUM(I52:I52) -> 1700000 | J53: =SUM(J52:J52) -> 1700000 | ... L53: =SUM(L52:L52) -> 1700000
A55: Cálculo del Capital de Trabajo
A56: Concepto | B56: Cobertura | C56: Año 1 | D56: Año 2 | E56: Año 3 | F56: Año 4 | G56: Año 5 | H56: Año 6 | I56: Año 7 | J56: Año 8 | K56: Año 9 | L56: Año 10
A57: Activo circulante | C57: =C58 -> 450000 | D57: =D58 -> 700000 | E57: =E58 -> 950000 | F57: =F58 -> 1200000 | G57: =G58 -> 1450000 | H57: =H58 -> 1700000 | I57: =I58 -> 1700000 | J57: =J58 -> 1700000 | ... L57: =L58 -> 1700000
A58: Efectivo | C58: =C53 -> 450000 | D58: =D53 -> 700000 | E58: =E53 -> 950000 | F58: =F53 -> 1200000 | G58: =G53 -> 1450000 | H58: =H53 -> 1700000 | I58: =I53 -> 1700000 | J58: =J53 -> 1700000 | ... L58: =L53 -> 1700000
A59: Pasivo circulante | C59: =SUM(C60:C61) -> 0 | D59: =SUM(D60:D61) -> 0 | E59: =SUM(E60:E61) -> 0 | F59: =SUM(F60:F61) -> 0 | G59: =SUM(G60:G61) -> 0 | H59: =SUM(H60:H61) -> 0 | I59: =SUM(I60:I61) -> 0 | J59: =SUM(J60:J61) -> 0 | ... L59: =SUM(L60:L61) -> 0
A60: Cuentas por pagar | C60: 0 | D60: 0 | E60: 0 | F60: 0 | G60: 0 | H60: 0 | I60: 0 | J60: 0 | K60: 0 | L60: 0
A61: Proveedores | C61: 0 | D61: 0 | E61: 0 | F61: 0 | G61: 0 | H61: 0 | I61: 0 | J61: 0 | K61: 0 | L61: 0
A62: Capital de Trabajo (Ac - Pc) | C62: =C57-C59 -> 450000 | D62: =D57-D59 -> 700000 | E62: =E57-E59 -> 950000 | F62: =F57-F59 -> 1200000 | G62: =G57-G59 -> 1450000 | H62: =H57-H59 -> 1700000 | I62: =I57-I59 -> 1700000 | J62: =J57-J59 -> 1700000 | ... L62: =L57-L59 -> 1700000
A63: Incremento Capital Trabajo | B63: =C62-B62 -> 450000 | C63: =D62-C62 -> 250000 | D63: =E62-D62 -> 250000 | E63: =F62-E62 -> 250000 | F63: =G62-F62 -> 250000 | G63: =H62-G62 -> 250000 | H63: =I62-H62 -> 0 | I63: =J62-I62 -> 0 | ... L63: =M62-L62 -> -1700000
A65: 5. Inversiones
A66: Calendario de inversiones
A67: Concepto | B67: Año 0 | C67: Año 1 | D67: Año 2 | E67: Año 3 | F67: Año 4 | G67: Año 5 | H67: Año 6 | I67: Año 7 | J67: Año 8 | K67: Año 9 | L67: Año 10
A68: Activos Fijos
A69: Inversiones a 20 años | B69: 100000
A70: Inversiones a 10 años | B70: =3000000+200000+450000+50000 -> 3700000
A71: Inversiones a 5 años | B71: =300000+100000 -> 400000
A72: Inversion terrenos | B72: 750000
A73: Gastos Pre-operativos
A74: Gastos puesta en marcha | B74: 0
A75: Capital de trabajo
A76: Capital de trabajo | B76: =B63 -> 450000 | C76: =C63 -> 250000 | D76: =D63 -> 250000 | E76: =E63 -> 250000 | F76: =F63 -> 250000 | G76: =G63 -> 250000 | H76: =H63 -> 0 | I76: =I63 -> 0 | ... L76: =L63 -> -1700000
A77: Total Inversiones | B77: =SUM(B68:B76) -> 5400000 | C77: =SUM(C68:C76) -> 250000 | D77: =SUM(D68:D76) -> 250000 | E77: =SUM(E68:E76) -> 250000 | F77: =SUM(F68:F76) -> 250000 | G77: =SUM(G68:G76) -> 250000 | H77: =SUM(H68:H76) -> 0 | I77: =SUM(I68:I76) -> 0 | ... L77: =SUM(L68:L76) -> -1700000
A79: 6. Depreciaciones y Amortizaciones
A80: Calendario de Depreciaciones y Amortizaciones
A81: Concepto | B81: Año 0 | C81: Año 1 | D81: Año 2 | E81: Año 3 | F81: Año 4 | G81: Año 5 | H81: Año 6 | I81: Año 7 | J81: Año 8 | K81: Año 9 | L81: Año 10 | R81: Inversión | S81: Valor Activo | T81: Valor residual | U81: Vida útil | V81: Dep. Anual
A82: Inversiones a 20 años | C82: =$V$82 -> 2500 | D82: =$V$82 -> 2500 | E82: =$V$82 -> 2500 | F82: =$V$82 -> 2500 | G82: =$V$82 -> 2500 | H82: =$V$82 -> 2500 | I82: =$V$82 -> 2500 | J82: =$V$82 -> 2500 | ... L82: =$V$82 -> 2500 | R82: Edificio | S82: =B69 -> 100000 | T82: 50000 | U82: 20 | V82: =(S82-T82)/U82 -> 2500
A83: Inversiones a 10 años | C83: =$V$83+$V$84 -> 270000 | D83: =$V$83+$V$84 -> 270000 | E83: =$V$83+$V$84 -> 270000 | F83: =$V$83+$V$84 -> 270000 | G83: =$V$83+$V$84 -> 270000 | H83: =$V$83+$V$84 -> 270000 | I83: =$V$83+$V$84 -> 270000 | J83: =$V$83+$V$84 -> 270000 | ... L83: =$V$83+$V$84 -> 270000 | R83: Estanque y canales | S83: 3000000 | T83: 1000000 | U83: 10 | V83: =(S83-T83)/U83 -> 200000
A84: Inversiones a 5 años | C84: =$V$85 -> 80000 | D84: =$V$85 -> 80000 | E84: =$V$85 -> 80000 | F84: =$V$85 -> 80000 | G84: =$V$85 -> 80000 | H84: 0 | I84: 0 | J84: 0 | K84: 0 | L84: 0 | R84: Maq & Equipo | S84: =B70-S83 -> 700000 | T84: 0 | U84: 10 | V84: =(S84-T84)/U84 -> 70000
A85: Total Depreciación | C85: =SUM(C82:C84) -> 352500 | D85: =SUM(D82:D84) -> 352500 | E85: =SUM(E82:E84) -> 352500 | F85: =SUM(F82:F84) -> 352500 | G85: =SUM(G82:G84) -> 352500 | H85: =SUM(H82:H84) -> 272500 | I85: =SUM(I82:I84) -> 272500 | J85: =SUM(J82:J84) -> 272500 | ... L85: =SUM(L82:L84) -> 272500 | R85: Vehículos y embarcaciones | S85: =B71 -> 400000 | T85: 0 | U85: 5 | V85: =(S85-T85)/U85 -> 80000
S86: =SUM(S82:S85) -> 4200000
A87: Amortización pre-operativos | C87: =$B$74/10 -> 0 | D87: =$B$74/10 -> 0 | E87: =$B$74/10 -> 0 | F87: =$B$74/10 -> 0 | G87: =$B$74/10 -> 0 | H87: =$B$74/10 -> 0 | I87: =$B$74/10 -> 0 | J87: =$B$74/10 -> 0 | ... L87: =$B$74/10 -> 0
A88: Total Amortización | C88: =SUM(C87) -> 0 | D88: =SUM(D87) -> 0 | E88: =SUM(E87) -> 0 | F88: =SUM(F87) -> 0 | G88: =SUM(G87) -> 0 | H88: =SUM(H87) -> 0 | I88: =SUM(I87) -> 0 | J88: =SUM(J87) -> 0 | ... L88: =SUM(L87) -> 0
A90: 7. Valor de desecho del proyecto
A91: Clalculo del valor de desecho del proyecto (método contable)
A92: Concepto | B92: Valor del | C92: Depreciación por periodo | M92: Valor de
B93: Activo | C93: Año 1 | D93: Año 2 | E93: Año 3 | F93: Año 4 | G93: Año 5 | H93: Año 6 | I93: Año 7 | J93: Año 8 | K93: Año 9 | L93: Año 10 | M93: Desecho
A94: Inversiones a 20 años | B94: =B69 -> 100000 | C94: =C82 -> 2500 | D94: =D82 -> 2500 | E94: =E82 -> 2500 | F94: =F82 -> 2500 | G94: =G82 -> 2500 | H94: =H82 -> 2500 | I94: =I82 -> 2500 | J94: =J82 -> 2500 | ... L94: =L82 -> 2500 | M94: =B94-SUM(C94:L94) -> 75000
A95: Inversiones a 10 años | B95: =B70 -> 3700000 | C95: =C83 -> 270000 | D95: =D83 -> 270000 | E95: =E83 -> 270000 | F95: =F83 -> 270000 | G95: =G83 -> 270000 | H95: =H83 -> 270000 | I95: =I83 -> 270000 | J95: =J83 -> 270000 | ... L95: =L83 -> 270000 | M95: =B95-SUM(C95:L95) -> 1000000
A96: Inversiones a 5 años | B96: =B71 -> 400000 | C96: =C84 -> 80000 | D96: =D84 -> 80000 | E96: =E84 -> 80000 | F96: =F84 -> 80000 | G96: =G84 -> 80000 | H96: =H84 -> 0 | I96: =I84 -> 0 | J96: =J84 -> 0 | ... L96: =L84 -> 0 | M96: =B96-SUM(C96:L96) -> 0
A97: Amortización pre-operativos | B97: =B74 -> 0 | C97: =C87 -> 0 | D97: =D87 -> 0 | E97: =E87 -> 0 | F97: =F87 -> 0 | G97: =G87 -> 0 | H97: =H87 -> 0 | I97: =I87 -> 0 | J97: =J87 -> 0 | ... L97: =L87 -> 0 | M97: =B97-SUM(C97:L97) -> 0
A98: Valor de desecho total | M98: =SUM(M94:M97) -> 1075000
A100: 8. Financiamiento | J100: C = | K100: =B102 -> 2700000
A101: Cálculo del Financiamiento | J101: i* = | K101: =B103 -> 0.1
A102: Financiamiento bancario (valor) | B102: =B77*E102 -> 2700000 | E102: 0.5 | J102: n = | K102: 5 | L102: Años
A103: Financiamiento bancario (tasa) | B103: =B22 -> 0.1 | J103: i = | K103: =K101/(1-K101) -> 0.11111111
A104: Financiamiento bancario (periodos) | B104: 7 | C104: años | J104: C* = | K104: =K100*(1-K101) -> 2430000
A105: Modalidad | B105: Pagos exactos | J105: A = | K105: =PMT(K103,K102,-K104) -> 659324.56
E106: 1 | F106: 2 | G106: 3 | H106: 4 | I106: 5
A107: Concepto | B107: Año 0 | C107: Año 1 | D107: Año 2 | E107: Año 3 | F107: Año 4 | G107: Año 5 | H107: Año 6 | I107: Año 7
A108: Saldo crédito | B108: =B102 -> 2700000 | C108: =B108-C111 -> 2700000 | D108: =C108-D111 -> 2700000 | E108: =D108-E111 -> 2267417.2 | F108: =E108-F111 -> 1786769.6 | G108: =F108-G111 -> 1252716.7 | H108: =G108-H111 -> 659324.56 | I108: =H108-I111 -> 0
A109: Cuota mensual (anualidad) | B109: =B110 -> 270000 | C109: =C110 -> 270000 | D109: =D110 -> 270000 | E109: =$K$105 -> 659324.56 | F109: =$K$105 -> 659324.56 | G109: =$K$105 -> 659324.56 | H109: =$K$105 -> 659324.56 | I109: =$K$105 -> 659324.56
A110: Intereses | B110: =B108*$B$103 -> 270000 | C110: =B108*$B$103 -> 270000 | D110: =C108*$B$103 -> 270000 | E110: =E108*$B$103 -> 226741.72 | F110: =F108*$B$103 -> 178676.96 | G110: =G108*$B$103 -> 125271.67 | H110: =H108*$B$103 -> 65932.456 | I110: =I108*$B$103 -> 0
A111: Abono a capital (amortización) | C111: =C109-C110 -> 0 | D111: =D109-D110 -> 0 | E111: =((E109*(1-$K$101)^($K$102-E106))) -> 432582.84 | F111: =((F109*(1-$K$101)^($K$102-F106))) -> 480647.6 | G111: =((G109*(1-$K$101)^($K$102-G106))) -> 534052.89 | H111: =((H109*(1-$K$101)^($K$102-H106))) -> 593392.1 | I111: =((I109*(1-$K$101)^($K$102-I106))) -> 659324.56
...
